[{"ward_num":"1","srch_fr_e":518,"srch_which_got_e":425,"srch_fr_q":182,"srch_which_got_q":65,"booking":65,"ongng_ride":0,"done_ride":33,"cancel_ride":32,"drvr_cancel":10,"rider_cancel":22,"earning":10103,"dist":590.619,"avg_dist_pr_trip":17.8975,"avg_fare":306.1515,"srch_to_e_rate":0.8205,"e_to_q_srch_rate":0.4282,"q_accept_rate":0.3571,"q_to_bkng_rate":1,"bkng_cancel_rate":0.4923,"cnvr_rate":0.0637},{"ward_num":"2","srch_fr_e":726,"srch_which_got_e":630,"srch_fr_q":207,"srch_which_got_q":82,"booking":82,"ongng_ride":0,"done_ride":51,"cancel_ride":31,"drvr_cancel":9,"rider_cancel":21,"earning":14951,"dist":904.06,"avg_dist_pr_trip":17.7267,"avg_fare":293.1569,"srch_to_e_rate":0.8678,"e_to_q_srch_rate":0.3286,"q_accept_rate":0.3961,"q_to_bkng_rate":1,"bkng_cancel_rate":0.378,"cnvr_rate":0.0702},{"ward_num":"3","srch_fr_e":439,"srch_which_got_e":432,"srch_fr_q":96,"srch_which_got_q":49,"booking":49,"ongng_ride":0,"done_ride":20,"cancel_ride":29,"drvr_cancel":11,"rider_cancel":18,"earning":6116,"dist":373.496,"avg_dist_pr_trip":18.6748,"avg_fare":305.8,"srch_to_e_rate":0.9841,"e_to_q_srch_rate":0.2222,"q_accept_rate":0.5104,"q_to_bkng_rate":1,"bkng_cancel_rate":0.5918,"cnvr_rate":0.0456},{"ward_num":"4","srch_fr_e":896,"srch_which_got_e":889,"srch_fr_q":229,"srch_which_got_q":84,"booking":82,"ongng_ride":0,"done_ride":41,"cancel_ride":41,"drvr_cancel":16,"rider_cancel":25,"earning":11708,"dist":637.056,"avg_dist_pr_trip":15.538,"avg_fare":285.561,"srch_to_e_rate":0.9922,"e_to_q_srch_rate":0.2576,"q_accept_rate":0.3668,"q_to_bkng_rate":0.9762,"bkng_cancel_rate":0.5,"cnvr_rate":0.0458},{"ward_num":"5","srch_fr_e":2064,"srch_which_got_e":2040,"srch_fr_q":505,"srch_which_got_q":288,"booking":286,"ongng_ride":0,"done_ride":151,"cancel_ride":135,"drvr_cancel":59,"rider_cancel":75,"earning":30252,"dist":1642.031,"avg_dist_pr_trip":10.8744,"avg_fare":200.3444,"srch_to_e_rate":0.9884,"e_to_q_srch_rate":0.2475,"q_accept_rate":0.5703,"q_to_bkng_rate":0.9931,"bkng_cancel_rate":0.472,"cnvr_rate":0.0732},{"ward_num":"6","srch_fr_e":1163,"srch_which_got_e":1153,"srch_fr_q":334,"srch_which_got_q":155,"booking":155,"ongng_ride":0,"done_ride":73,"cancel_ride":82,"drvr_cancel":42,"rider_cancel":39,"earning":15303,"dist":897.917,"avg_dist_pr_trip":12.3002,"avg_fare":209.6301,"srch_to_e_rate":0.9914,"e_to_q_srch_rate":0.2897,"q_accept_rate":0.4641,"q_to_bkng_rate":1,"bkng_cancel_rate":0.529,"cnvr_rate":0.0628},{"ward_num":"7","srch_fr_e":1831,"srch_which_got_e":1812,"srch_fr_q":585,"srch_which_got_q":211,"booking":209,"ongng_ride":0,"done_ride":89,"cancel_ride":120,"drvr_cancel":52,"rider_cancel":66,"earning":20958,"dist":1118.601,"avg_dist_pr_trip":12.5686,"avg_fare":235.4831,"srch_to_e_rate":0.9896,"e_to_q_srch_rate":0.3228,"q_accept_rate":0.3607,"q_to_bkng_rate":0.9905,"bkng_cancel_rate":0.5742,"cnvr_rate":0.0486},{"ward_num":"8","srch_fr_e":834,"srch_which_got_e":828,"srch_fr_q":236,"srch_which_got_q":130,"booking":130,"ongng_ride":0,"done_ride":66,"cancel_ride":64,"drvr_cancel":28,"rider_cancel":34,"earning":11913,"dist":646.246,"avg_dist_pr_trip":9.7916,"avg_fare":180.5,"srch_to_e_rate":0.9928,"e_to_q_srch_rate":0.285,"q_accept_rate":0.5508,"q_to_bkng_rate":1,"bkng_cancel_rate":0.4923,"cnvr_rate":0.0791},{"ward_num":"9","srch_fr_e":781,"srch_which_got_e":777,"srch_fr_q":198,"srch_which_got_q":148,"booking":146,"ongng_ride":0,"done_ride":88,"cancel_ride":58,"drvr_cancel":30,"rider_cancel":28,"earning":15200,"dist":843.668,"avg_dist_pr_trip":9.5871,"avg_fare":172.7273,"srch_to_e_rate":0.9949,"e_to_q_srch_rate":0.2548,"q_accept_rate":0.7475,"q_to_bkng_rate":0.9865,"bkng_cancel_rate":0.3973,"cnvr_rate":0.1127},{"ward_num":"10","srch_fr_e":1461,"srch_which_got_e":1460,"srch_fr_q":395,"srch_which_got_q":243,"booking":243,"ongng_ride":0,"done_ride":143,"cancel_ride":100,"drvr_cancel":46,"rider_cancel":54,"earning":28142,"dist":1592.389,"avg_dist_pr_trip":11.1356,"avg_fare":196.7972,"srch_to_e_rate":0.9993,"e_to_q_srch_rate":0.2705,"q_accept_rate":0.6152,"q_to_bkng_rate":1,"bkng_cancel_rate":0.4115,"cnvr_rate":0.0979},{"ward_num":"11","srch_fr_e":1775,"srch_which_got_e":1762,"srch_fr_q":542,"srch_which_got_q":372,"booking":372,"ongng_ride":0,"done_ride":215,"cancel_ride":157,"drvr_cancel":75,"rider_cancel":81,"earning":46152,"dist":2569.655,"avg_dist_pr_trip":11.9519,"avg_fare":214.6605,"srch_to_e_rate":0.9927,"e_to_q_srch_rate":0.3076,"q_accept_rate":0.6863,"q_to_bkng_rate":1,"bkng_cancel_rate":0.422,"cnvr_rate":0.1211},{"ward_num":"12","srch_fr_e":1678,"srch_which_got_e":1671,"srch_fr_q":483,"srch_which_got_q":326,"booking":325,"ongng_ride":0,"done_ride":183,"cancel_ride":142,"drvr_cancel":73,"rider_cancel":69,"earning":31922,"dist":1807.497,"avg_dist_pr_trip":9.877,"avg_fare":174.4372,"srch_to_e_rate":0.9958,"e_to_q_srch_rate":0.289,"q_accept_rate":0.6749,"q_to_bkng_rate":0.9969,"bkng_cancel_rate":0.4369,"cnvr_rate":0.1091},{"ward_num":"13","srch_fr_e":1489,"srch_which_got_e":1486,"srch_fr_q":511,"srch_which_got_q":341,"booking":341,"ongng_ride":0,"done_ride":193,"cancel_ride":148,"drvr_cancel":75,"rider_cancel":70,"earning":31167,"dist":1771.056,"avg_dist_pr_trip":9.1765,"avg_fare":161.487,"srch_to_e_rate":0.998,"e_to_q_srch_rate":0.3439,"q_accept_rate":0.6673,"q_to_bkng_rate":1,"bkng_cancel_rate":0.434,"cnvr_rate":0.1296},{"ward_num":"14","srch_fr_e":665,"srch_which_got_e":661,"srch_fr_q":195,"srch_which_got_q":126,"booking":126,"ongng_ride":0,"done_ride":63,"cancel_ride":63,"drvr_cancel":36,"rider_cancel":27,"earning":11146,"dist":586.966,"avg_dist_pr_trip":9.3169,"avg_fare":176.9206,"srch_to_e_rate":0.994,"e_to_q_srch_rate":0.295,"q_accept_rate":0.6462,"q_to_bkng_rate":1,"bkng_cancel_rate":0.5,"cnvr_rate":0.0947},{"ward_num":"15","srch_fr_e":614,"srch_which_got_e":551,"srch_fr_q":121,"srch_which_got_q":63,"booking":63,"ongng_ride":0,"done_ride":33,"cancel_ride":30,"drvr_cancel":6,"rider_cancel":24,"earning":8401,"dist":492.789,"avg_dist_pr_trip":14.933,"avg_fare":254.5758,"srch_to_e_rate":0.8974,"e_to_q_srch_rate":0.2196,"q_accept_rate":0.5207,"q_to_bkng_rate":1,"bkng_cancel_rate":0.4762,"cnvr_rate":0.0537},{"ward_num":"16","srch_fr_e":865,"srch_which_got_e":817,"srch_fr_q":264,"srch_which_got_q":86,"booking":86,"ongng_ride":0,"done_ride":38,"cancel_ride":48,"drvr_cancel":19,"rider_cancel":29,"earning":9738,"dist":602.939,"avg_dist_pr_trip":15.8668,"avg_fare":256.2632,"srch_to_e_rate":0.9445,"e_to_q_srch_rate":0.3231,"q_accept_rate":0.3258,"q_to_bkng_rate":1,"bkng_cancel_rate":0.5581,"cnvr_rate":0.0439},{"ward_num":"17","srch_fr_e":457,"srch_which_got_e":398,"srch_fr_q":181,"srch_which_got_q":21,"booking":21,"ongng_ride":0,"done_ride":10,"cancel_ride":11,"drvr_cancel":5,"rider_cancel":6,"earning":1982,"dist":115.063,"avg_dist_pr_trip":11.5063,"avg_fare":198.2,"srch_to_e_rate":0.8709,"e_to_q_srch_rate":0.4548,"q_accept_rate":0.116,"q_to_bkng_rate":1,"bkng_cancel_rate":0.5238,"cnvr_rate":0.0219},{"ward_num":"18","srch_fr_e":613,"srch_which_got_e":590,"srch_fr_q":159,"srch_which_got_q":52,"booking":52,"ongng_ride":0,"done_ride":18,"cancel_ride":34,"drvr_cancel":14,"rider_cancel":20,"earning":4146,"dist":198.307,"avg_dist_pr_trip":11.0171,"avg_fare":230.3333,"srch_to_e_rate":0.9625,"e_to_q_srch_rate":0.2695,"q_accept_rate":0.327,"q_to_bkng_rate":1,"bkng_cancel_rate":0.6538,"cnvr_rate":0.0294},{"ward_num":"19","srch_fr_e":3346,"srch_which_got_e":3290,"srch_fr_q":1028,"srch_which_got_q":548,"booking":545,"ongng_ride":0,"done_ride":273,"cancel_ride":272,"drvr_cancel":125,"rider_cancel":145,"earning":59931,"dist":3373.742,"avg_dist_pr_trip":12.358,"avg_fare":219.5275,"srch_to_e_rate":0.9833,"e_to_q_srch_rate":0.3125,"q_accept_rate":0.5331,"q_to_bkng_rate":0.9945,"bkng_cancel_rate":0.4991,"cnvr_rate":0.0816},{"ward_num":"20","srch_fr_e":546,"srch_which_got_e":545,"srch_fr_q":138,"srch_which_got_q":68,"booking":67,"ongng_ride":0,"done_ride":34,"cancel_ride":33,"drvr_cancel":17,"rider_cancel":16,"earning":7873,"dist":453.922,"avg_dist_pr_trip":13.3506,"avg_fare":231.5588,"srch_to_e_rate":0.9982,"e_to_q_srch_rate":0.2532,"q_accept_rate":0.4928,"q_to_bkng_rate":0.9853,"bkng_cancel_rate":0.4925,"cnvr_rate":0.0623},{"ward_num":"21","srch_fr_e":782,"srch_which_got_e":775,"srch_fr_q":222,"srch_which_got_q":104,"booking":104,"ongng_ride":0,"done_ride":52,"cancel_ride":52,"drvr_cancel":29,"rider_cancel":22,"earning":12665,"dist":766.713,"avg_dist_pr_trip":14.7445,"avg_fare":243.5577,"srch_to_e_rate":0.991,"e_to_q_srch_rate":0.2865,"q_accept_rate":0.4685,"q_to_bkng_rate":1,"bkng_cancel_rate":0.5,"cnvr_rate":0.0665},{"ward_num":"22","srch_fr_e":3518,"srch_which_got_e":3452,"srch_fr_q":1102,"srch_which_got_q":491,"booking":487,"ongng_ride":0,"done_ride":207,"cancel_ride":280,"drvr_cancel":147,"rider_cancel":133,"earning":47121,"dist":2678.093,"avg_dist_pr_trip":12.9376,"avg_fare":227.6377,"srch_to_e_rate":0.9812,"e_to_q_srch_rate":0.3192,"q_accept_rate":0.4456,"q_to_bkng_rate":0.9919,"bkng_cancel_rate":0.5749,"cnvr_rate":0.0588},{"ward_num":"23","srch_fr_e":1927,"srch_which_got_e":1912,"srch_fr_q":667,"srch_which_got_q":290,"booking":288,"ongng_ride":0,"done_ride":145,"cancel_ride":143,"drvr_cancel":78,"rider_cancel":63,"earning":33120,"dist":1855.058,"avg_dist_pr_trip":12.7935,"avg_fare":228.4138,"srch_to_e_rate":0.9922,"e_to_q_srch_rate":0.3488,"q_accept_rate":0.4348,"q_to_bkng_rate":0.9931,"bkng_cancel_rate":0.4965,"cnvr_rate":0.0752},{"ward_num":"24","srch_fr_e":7117,"srch_which_got_e":7070,"srch_fr_q":2539,"srch_which_got_q":1139,"booking":1134,"ongng_ride":0,"done_ride":620,"cancel_ride":514,"drvr_cancel":272,"rider_cancel":238,"earning":119330,"dist":6597.532,"avg_dist_pr_trip":10.6412,"avg_fare":192.4677,"srch_to_e_rate":0.9934,"e_to_q_srch_rate":0.3591,"q_accept_rate":0.4486,"q_to_bkng_rate":0.9956,"bkng_cancel_rate":0.4533,"cnvr_rate":0.0871},{"ward_num":"25","srch_fr_e":2536,"srch_which_got_e":2521,"srch_fr_q":876,"srch_which_got_q":433,"booking":433,"ongng_ride":0,"done_ride":255,"cancel_ride":178,"drvr_cancel":93,"rider_cancel":82,"earning":51891,"dist":2887.35,"avg_dist_pr_trip":11.3229,"avg_fare":203.4941,"srch_to_e_rate":0.9941,"e_to_q_srch_rate":0.3475,"q_accept_rate":0.4943,"q_to_bkng_rate":1,"bkng_cancel_rate":0.4111,"cnvr_rate":0.1006},{"ward_num":"26","srch_fr_e":8652,"srch_which_got_e":8615,"srch_fr_q":3255,"srch_which_got_q":1627,"booking":1619,"ongng_ride":0,"done_ride":880,"cancel_ride":739,"drvr_cancel":384,"rider_cancel":348,"earning":158225,"dist":8546.023,"avg_dist_pr_trip":9.7114,"avg_fare":179.8011,"srch_to_e_rate":0.9957,"e_to_q_srch_rate":0.3778,"q_accept_rate":0.4998,"q_to_bkng_rate":0.9951,"bkng_cancel_rate":0.4565,"cnvr_rate":0.1017},{"ward_num":"27","srch_fr_e":3290,"srch_which_got_e":3237,"srch_fr_q":1168,"srch_which_got_q":452,"booking":448,"ongng_ride":0,"done_ride":229,"cancel_ride":217,"drvr_cancel":117,"rider_cancel":99,"earning":49452,"dist":2742.033,"avg_dist_pr_trip":11.9739,"avg_fare":215.9476,"srch_to_e_rate":0.9839,"e_to_q_srch_rate":0.3608,"q_accept_rate":0.387,"q_to_bkng_rate":0.9912,"bkng_cancel_rate":0.4844,"cnvr_rate":0.0696},{"ward_num":"28","srch_fr_e":3303,"srch_which_got_e":3278,"srch_fr_q":1138,"srch_which_got_q":526,"booking":521,"ongng_ride":0,"done_ride":246,"cancel_ride":275,"drvr_cancel":136,"rider_cancel":135,"earning":54075,"dist":3011.808,"avg_dist_pr_trip":12.2431,"avg_fare":219.8171,"srch_to_e_rate":0.9924,"e_to_q_srch_rate":0.3472,"q_accept_rate":0.4622,"q_to_bkng_rate":0.9905,"bkng_cancel_rate":0.5278,"cnvr_rate":0.0745},{"ward_num":"29","srch_fr_e":930,"srch_which_got_e":912,"srch_fr_q":316,"srch_which_got_q":121,"booking":120,"ongng_ride":0,"done_ride":66,"cancel_ride":54,"drvr_cancel":27,"rider_cancel":26,"earning":15163,"dist":806.772,"avg_dist_pr_trip":12.2238,"avg_fare":229.7424,"srch_to_e_rate":0.9806,"e_to_q_srch_rate":0.3465,"q_accept_rate":0.3829,"q_to_bkng_rate":0.9917,"bkng_cancel_rate":0.45,"cnvr_rate":0.071},{"ward_num":"30","srch_fr_e":2355,"srch_which_got_e":2329,"srch_fr_q":791,"srch_which_got_q":426,"booking":424,"ongng_ride":0,"done_ride":228,"cancel_ride":196,"drvr_cancel":102,"rider_cancel":93,"earning":45848,"dist":2531.392,"avg_dist_pr_trip":11.1026,"avg_fare":201.0877,"srch_to_e_rate":0.989,"e_to_q_srch_rate":0.3396,"q_accept_rate":0.5386,"q_to_bkng_rate":0.9953,"bkng_cancel_rate":0.4623,"cnvr_rate":0.0968},{"ward_num":"31","srch_fr_e":2899,"srch_which_got_e":2886,"srch_fr_q":1259,"srch_which_got_q":557,"booking":555,"ongng_ride":0,"done_ride":307,"cancel_ride":248,"drvr_cancel":133,"rider_cancel":110,"earning":45094,"dist":2405.789,"avg_dist_pr_trip":7.8364,"avg_fare":146.886,"srch_to_e_rate":0.9955,"e_to_q_srch_rate":0.4362,"q_accept_rate":0.4424,"q_to_bkng_rate":0.9964,"bkng_cancel_rate":0.4468,"cnvr_rate":0.1059},{"ward_num":"32","srch_fr_e":3024,"srch_which_got_e":2994,"srch_fr_q":1088,"srch_which_got_q":607,"booking":604,"ongng_ride":0,"done_ride":339,"cancel_ride":265,"drvr_cancel":148,"rider_cancel":116,"earning":52980,"dist":2757.287,"avg_dist_pr_trip":8.1336,"avg_fare":156.2832,"srch_to_e_rate":0.9901,"e_to_q_srch_rate":0.3634,"q_accept_rate":0.5579,"q_to_bkng_rate":0.9951,"bkng_cancel_rate":0.4387,"cnvr_rate":0.1121},{"ward_num":"33","srch_fr_e":8846,"srch_which_got_e":8810,"srch_fr_q":3424,"srch_which_got_q":1626,"booking":1622,"ongng_ride":0,"done_ride":827,"cancel_ride":795,"drvr_cancel":385,"rider_cancel":404,"earning":137374,"dist":7183.283,"avg_dist_pr_trip":8.686,"avg_fare":166.1112,"srch_to_e_rate":0.9959,"e_to_q_srch_rate":0.3886,"q_accept_rate":0.4749,"q_to_bkng_rate":0.9975,"bkng_cancel_rate":0.4901,"cnvr_rate":0.0935},{"ward_num":"34","srch_fr_e":7724,"srch_which_got_e":7701,"srch_fr_q":2927,"srch_which_got_q":1516,"booking":1512,"ongng_ride":0,"done_ride":770,"cancel_ride":742,"drvr_cancel":409,"rider_cancel":330,"earning":136493,"dist":7434.755,"avg_dist_pr_trip":9.6555,"avg_fare":177.2636,"srch_to_e_rate":0.997,"e_to_q_srch_rate":0.3801,"q_accept_rate":0.5179,"q_to_bkng_rate":0.9974,"bkng_cancel_rate":0.4907,"cnvr_rate":0.0997},{"ward_num":"35","srch_fr_e":10194,"srch_which_got_e":10158,"srch_fr_q":3961,"srch_which_got_q":2292,"booking":2282,"ongng_ride":0,"done_ride":1226,"cancel_ride":1056,"drvr_cancel":580,"rider_cancel":471,"earning":197461,"dist":10473.3,"avg_dist_pr_trip":8.5427,"avg_fare":161.0612,"srch_to_e_rate":0.9965,"e_to_q_srch_rate":0.3899,"q_accept_rate":0.5786,"q_to_bkng_rate":0.9956,"bkng_cancel_rate":0.4628,"cnvr_rate":0.1203},{"ward_num":"36","srch_fr_e":8158,"srch_which_got_e":8133,"srch_fr_q":3347,"srch_which_got_q":1910,"booking":1907,"ongng_ride":0,"done_ride":967,"cancel_ride":939,"drvr_cancel":509,"rider_cancel":421,"earning":154229,"dist":7806.034,"avg_dist_pr_trip":8.0724,"avg_fare":159.4922,"srch_to_e_rate":0.9969,"e_to_q_srch_rate":0.4115,"q_accept_rate":0.5707,"q_to_bkng_rate":0.9984,"bkng_cancel_rate":0.4924,"cnvr_rate":0.1185},{"ward_num":"37","srch_fr_e":7327,"srch_which_got_e":7312,"srch_fr_q":3068,"srch_which_got_q":1741,"booking":1732,"ongng_ride":0,"done_ride":1030,"cancel_ride":701,"drvr_cancel":340,"rider_cancel":355,"earning":152318,"dist":7938.042,"avg_dist_pr_trip":7.7068,"avg_fare":147.8816,"srch_to_e_rate":0.998,"e_to_q_srch_rate":0.4196,"q_accept_rate":0.5675,"q_to_bkng_rate":0.9948,"bkng_cancel_rate":0.4047,"cnvr_rate":0.1406},{"ward_num":"38","srch_fr_e":3347,"srch_which_got_e":3316,"srch_fr_q":1204,"srch_which_got_q":578,"booking":578,"ongng_ride":0,"done_ride":281,"cancel_ride":297,"drvr_cancel":143,"rider_cancel":149,"earning":42691,"dist":2269.094,"avg_dist_pr_trip":8.0751,"avg_fare":151.9253,"srch_to_e_rate":0.9907,"e_to_q_srch_rate":0.3631,"q_accept_rate":0.4801,"q_to_bkng_rate":1,"bkng_cancel_rate":0.5138,"cnvr_rate":0.084},{"ward_num":"39","srch_fr_e":2168,"srch_which_got_e":2157,"srch_fr_q":787,"srch_which_got_q":475,"booking":475,"ongng_ride":0,"done_ride":253,"cancel_ride":222,"drvr_cancel":111,"rider_cancel":105,"earning":43462,"dist":2365.335,"avg_dist_pr_trip":9.3492,"avg_fare":171.7866,"srch_to_e_rate":0.9949,"e_to_q_srch_rate":0.3649,"q_accept_rate":0.6036,"q_to_bkng_rate":1,"bkng_cancel_rate":0.4674,"cnvr_rate":0.1167},{"ward_num":"41","srch_fr_e":1439,"srch_which_got_e":1432,"srch_fr_q":443,"srch_which_got_q":196,"booking":196,"ongng_ride":0,"done_ride":92,"cancel_ride":104,"drvr_cancel":59,"rider_cancel":44,"earning":19637,"dist":1158.503,"avg_dist_pr_trip":12.5924,"avg_fare":213.4457,"srch_to_e_rate":0.9951,"e_to_q_srch_rate":0.3094,"q_accept_rate":0.4424,"q_to_bkng_rate":1,"bkng_cancel_rate":0.5306,"cnvr_rate":0.0639},{"ward_num":"40","srch_fr_e":3623,"srch_which_got_e":3612,"srch_fr_q":1444,"srch_which_got_q":916,"booking":915,"ongng_ride":0,"done_ride":533,"cancel_ride":382,"drvr_cancel":203,"rider_cancel":175,"earning":74789,"dist":3797.568,"avg_dist_pr_trip":7.1249,"avg_fare":140.3171,"srch_to_e_rate":0.997,"e_to_q_srch_rate":0.3998,"q_accept_rate":0.6343,"q_to_bkng_rate":0.9989,"bkng_cancel_rate":0.4175,"cnvr_rate":0.1471},{"ward_num":"42","srch_fr_e":2636,"srch_which_got_e":2617,"srch_fr_q":1040,"srch_which_got_q":640,"booking":639,"ongng_ride":0,"done_ride":334,"cancel_ride":305,"drvr_cancel":170,"rider_cancel":130,"earning":52022,"dist":2753.743,"avg_dist_pr_trip":8.2447,"avg_fare":155.7545,"srch_to_e_rate":0.9928,"e_to_q_srch_rate":0.3974,"q_accept_rate":0.6154,"q_to_bkng_rate":0.9984,"bkng_cancel_rate":0.4773,"cnvr_rate":0.1267},{"ward_num":"43","srch_fr_e":2013,"srch_which_got_e":2001,"srch_fr_q":702,"srch_which_got_q":441,"booking":440,"ongng_ride":0,"done_ride":269,"cancel_ride":170,"drvr_cancel":83,"rider_cancel":84,"earning":40254,"dist":2184.218,"avg_dist_pr_trip":8.1198,"avg_fare":149.6431,"srch_to_e_rate":0.994,"e_to_q_srch_rate":0.3508,"q_accept_rate":0.6282,"q_to_bkng_rate":0.9977,"bkng_cancel_rate":0.3864,"cnvr_rate":0.1336},{"ward_num":"44","srch_fr_e":5666,"srch_which_got_e":5639,"srch_fr_q":2521,"srch_which_got_q":1483,"booking":1476,"ongng_ride":0,"done_ride":768,"cancel_ride":708,"drvr_cancel":412,"rider_cancel":291,"earning":111968,"dist":5913.794,"avg_dist_pr_trip":7.7003,"avg_fare":145.7917,"srch_to_e_rate":0.9952,"e_to_q_srch_rate":0.4471,"q_accept_rate":0.5883,"q_to_bkng_rate":0.9953,"bkng_cancel_rate":0.4797,"cnvr_rate":0.1355},{"ward_num":"45","srch_fr_e":5245,"srch_which_got_e":5235,"srch_fr_q":2459,"srch_which_got_q":1254,"booking":1252,"ongng_ride":0,"done_ride":587,"cancel_ride":665,"drvr_cancel":373,"rider_cancel":286,"earning":84716,"dist":4529.12,"avg_dist_pr_trip":7.7157,"avg_fare":144.3203,"srch_to_e_rate":0.9981,"e_to_q_srch_rate":0.4697,"q_accept_rate":0.51,"q_to_bkng_rate":0.9984,"bkng_cancel_rate":0.5312,"cnvr_rate":0.1119},{"ward_num":"46","srch_fr_e":1942,"srch_which_got_e":1937,"srch_fr_q":846,"srch_which_got_q":411,"booking":411,"ongng_ride":0,"done_ride":211,"cancel_ride":200,"drvr_cancel":110,"rider_cancel":89,"earning":31701,"dist":1713.733,"avg_dist_pr_trip":8.122,"avg_fare":150.2417,"srch_to_e_rate":0.9974,"e_to_q_srch_rate":0.4368,"q_accept_rate":0.4858,"q_to_bkng_rate":1,"bkng_cancel_rate":0.4866,"cnvr_rate":0.1087},{"ward_num":"47","srch_fr_e":2961,"srch_which_got_e":2958,"srch_fr_q":1318,"srch_which_got_q":450,"booking":449,"ongng_ride":0,"done_ride":195,"cancel_ride":254,"drvr_cancel":141,"rider_cancel":111,"earning":31875,"dist":1707.202,"avg_dist_pr_trip":8.7549,"avg_fare":163.4615,"srch_to_e_rate":0.999,"e_to_q_srch_rate":0.4456,"q_accept_rate":0.3414,"q_to_bkng_rate":0.9978,"bkng_cancel_rate":0.5657,"cnvr_rate":0.0659},{"ward_num":"48","srch_fr_e":3945,"srch_which_got_e":3928,"srch_fr_q":1539,"srch_which_got_q":924,"booking":921,"ongng_ride":0,"done_ride":469,"cancel_ride":451,"drvr_cancel":226,"rider_cancel":220,"earning":74737,"dist":3942.743,"avg_dist_pr_trip":8.4067,"avg_fare":159.3539,"srch_to_e_rate":0.9957,"e_to_q_srch_rate":0.3918,"q_accept_rate":0.6004,"q_to_bkng_rate":0.9968,"bkng_cancel_rate":0.4897,"cnvr_rate":0.1189},{"ward_num":"49","srch_fr_e":5460,"srch_which_got_e":5445,"srch_fr_q":2286,"srch_which_got_q":1530,"booking":1525,"ongng_ride":0,"done_ride":783,"cancel_ride":742,"drvr_cancel":431,"rider_cancel":306,"earning":126530,"dist":6819.564,"avg_dist_pr_trip":8.7095,"avg_fare":161.5964,"srch_to_e_rate":0.9973,"e_to_q_srch_rate":0.4198,"q_accept_rate":0.6693,"q_to_bkng_rate":0.9967,"bkng_cancel_rate":0.4866,"cnvr_rate":0.1434},{"ward_num":"50","srch_fr_e":5721,"srch_which_got_e":5705,"srch_fr_q":2518,"srch_which_got_q":1522,"booking":1516,"ongng_ride":0,"done_ride":866,"cancel_ride":650,"drvr_cancel":338,"rider_cancel":308,"earning":138877,"dist":7472.948,"avg_dist_pr_trip":8.6293,"avg_fare":160.3661,"srch_to_e_rate":0.9972,"e_to_q_srch_rate":0.4414,"q_accept_rate":0.6044,"q_to_bkng_rate":0.9961,"bkng_cancel_rate":0.4288,"cnvr_rate":0.1514},{"ward_num":"51","srch_fr_e":2716,"srch_which_got_e":2710,"srch_fr_q":1136,"srch_which_got_q":727,"booking":727,"ongng_ride":0,"done_ride":351,"cancel_ride":376,"drvr_cancel":193,"rider_cancel":177,"earning":54024,"dist":2845.417,"avg_dist_pr_trip":8.1066,"avg_fare":153.9145,"srch_to_e_rate":0.9978,"e_to_q_srch_rate":0.4192,"q_accept_rate":0.64,"q_to_bkng_rate":1,"bkng_cancel_rate":0.5172,"cnvr_rate":0.1292},{"ward_num":"52","srch_fr_e":5886,"srch_which_got_e":5877,"srch_fr_q":2448,"srch_which_got_q":1486,"booking":1480,"ongng_ride":0,"done_ride":769,"cancel_ride":711,"drvr_cancel":377,"rider_cancel":324,"earning":126430,"dist":6794.148,"avg_dist_pr_trip":8.835,"avg_fare":164.4083,"srch_to_e_rate":0.9985,"e_to_q_srch_rate":0.4165,"q_accept_rate":0.607,"q_to_bkng_rate":0.996,"bkng_cancel_rate":0.4804,"cnvr_rate":0.1306},{"ward_num":"53","srch_fr_e":4065,"srch_which_got_e":4052,"srch_fr_q":1509,"srch_which_got_q":674,"booking":673,"ongng_ride":0,"done_ride":332,"cancel_ride":341,"drvr_cancel":163,"rider_cancel":171,"earning":55344,"dist":2908.381,"avg_dist_pr_trip":8.7602,"avg_fare":166.6988,"srch_to_e_rate":0.9968,"e_to_q_srch_rate":0.3724,"q_accept_rate":0.4467,"q_to_bkng_rate":0.9985,"bkng_cancel_rate":0.5067,"cnvr_rate":0.0817},{"ward_num":"54","srch_fr_e":8038,"srch_which_got_e":8002,"srch_fr_q":3743,"srch_which_got_q":2078,"booking":2073,"ongng_ride":0,"done_ride":1030,"cancel_ride":1043,"drvr_cancel":485,"rider_cancel":545,"earning":135947,"dist":6856.984,"avg_dist_pr_trip":6.6573,"avg_fare":131.9874,"srch_to_e_rate":0.9955,"e_to_q_srch_rate":0.4678,"q_accept_rate":0.5552,"q_to_bkng_rate":0.9976,"bkng_cancel_rate":0.5031,"cnvr_rate":0.1281},{"ward_num":"55","srch_fr_e":7903,"srch_which_got_e":7870,"srch_fr_q":3646,"srch_which_got_q":2073,"booking":2068,"ongng_ride":0,"done_ride":958,"cancel_ride":1110,"drvr_cancel":563,"rider_cancel":544,"earning":140696,"dist":7407.158,"avg_dist_pr_trip":7.7319,"avg_fare":146.8643,"srch_to_e_rate":0.9958,"e_to_q_srch_rate":0.4633,"q_accept_rate":0.5686,"q_to_bkng_rate":0.9976,"bkng_cancel_rate":0.5368,"cnvr_rate":0.1212},{"ward_num":"56","srch_fr_e":6368,"srch_which_got_e":6355,"srch_fr_q":2901,"srch_which_got_q":1547,"booking":1541,"ongng_ride":0,"done_ride":749,"cancel_ride":792,"drvr_cancel":442,"rider_cancel":343,"earning":106701,"dist":5444.764,"avg_dist_pr_trip":7.2694,"avg_fare":142.4579,"srch_to_e_rate":0.998,"e_to_q_srch_rate":0.4565,"q_accept_rate":0.5333,"q_to_bkng_rate":0.9961,"bkng_cancel_rate":0.514,"cnvr_rate":0.1176},{"ward_num":"57","srch_fr_e":11230,"srch_which_got_e":11174,"srch_fr_q":5993,"srch_which_got_q":3509,"booking":3499,"ongng_ride":0,"done_ride":1363,"cancel_ride":2134,"drvr_cancel":1113,"rider_cancel":1005,"earning":199711,"dist":10397.811,"avg_dist_pr_trip":7.6286,"avg_fare":146.5231,"srch_to_e_rate":0.995,"e_to_q_srch_rate":0.5363,"q_accept_rate":0.5855,"q_to_bkng_rate":0.9972,"bkng_cancel_rate":0.6099,"cnvr_rate":0.1214},{"ward_num":"58","srch_fr_e":40801,"srch_which_got_e":40588,"srch_fr_q":18910,"srch_which_got_q":13676,"booking":13622,"ongng_ride":0,"done_ride":7442,"cancel_ride":6177,"drvr_cancel":3185,"rider_cancel":2951,"earning":1031700,"dist":49271.009,"avg_dist_pr_trip":6.6207,"avg_fare":138.6321,"srch_to_e_rate":0.9948,"e_to_q_srch_rate":0.4659,"q_accept_rate":0.7232,"q_to_bkng_rate":0.9961,"bkng_cancel_rate":0.4535,"cnvr_rate":0.1824},{"ward_num":"59","srch_fr_e":48188,"srch_which_got_e":47907,"srch_fr_q":18960,"srch_which_got_q":12913,"booking":12876,"ongng_ride":0,"done_ride":6177,"cancel_ride":6696,"drvr_cancel":3517,"rider_cancel":3119,"earning":1162460,"dist":61004.32,"avg_dist_pr_trip":9.876,"avg_fare":188.1917,"srch_to_e_rate":0.9942,"e_to_q_srch_rate":0.3958,"q_accept_rate":0.6811,"q_to_bkng_rate":0.9971,"bkng_cancel_rate":0.52,"cnvr_rate":0.1282},{"ward_num":"60","srch_fr_e":16127,"srch_which_got_e":16055,"srch_fr_q":7988,"srch_which_got_q":4235,"booking":4222,"ongng_ride":0,"done_ride":2025,"cancel_ride":2196,"drvr_cancel":1192,"rider_cancel":986,"earning":336024,"dist":17722.302,"avg_dist_pr_trip":8.7518,"avg_fare":165.9378,"srch_to_e_rate":0.9955,"e_to_q_srch_rate":0.4975,"q_accept_rate":0.5302,"q_to_bkng_rate":0.9969,"bkng_cancel_rate":0.5201,"cnvr_rate":0.1256},{"ward_num":"61","srch_fr_e":48974,"srch_which_got_e":48790,"srch_fr_q":22393,"srch_which_got_q":17058,"booking":17011,"ongng_ride":0,"done_ride":9686,"cancel_ride":7322,"drvr_cancel":3764,"rider_cancel":3501,"earning":1335412,"dist":64762.814,"avg_dist_pr_trip":6.6862,"avg_fare":137.8703,"srch_to_e_rate":0.9962,"e_to_q_srch_rate":0.459,"q_accept_rate":0.7618,"q_to_bkng_rate":0.9972,"bkng_cancel_rate":0.4304,"cnvr_rate":0.1978},{"ward_num":"62","srch_fr_e":7529,"srch_which_got_e":7510,"srch_fr_q":3637,"srch_which_got_q":2222,"booking":2218,"ongng_ride":0,"done_ride":1215,"cancel_ride":1002,"drvr_cancel":519,"rider_cancel":479,"earning":149433,"dist":7312.654,"avg_dist_pr_trip":6.0186,"avg_fare":122.9901,"srch_to_e_rate":0.9975,"e_to_q_srch_rate":0.4843,"q_accept_rate":0.6109,"q_to_bkng_rate":0.9982,"bkng_cancel_rate":0.4518,"cnvr_rate":0.1614},{"ward_num":"63","srch_fr_e":14113,"srch_which_got_e":14059,"srch_fr_q":7198,"srch_which_got_q":4682,"booking":4674,"ongng_ride":0,"done_ride":2449,"cancel_ride":2225,"drvr_cancel":1155,"rider_cancel":1054,"earning":331769,"dist":16424.248,"avg_dist_pr_trip":6.7065,"avg_fare":135.4712,"srch_to_e_rate":0.9962,"e_to_q_srch_rate":0.512,"q_accept_rate":0.6505,"q_to_bkng_rate":0.9983,"bkng_cancel_rate":0.476,"cnvr_rate":0.1735},{"ward_num":"64","srch_fr_e":15468,"srch_which_got_e":15410,"srch_fr_q":6869,"srch_which_got_q":3851,"booking":3839,"ongng_ride":0,"done_ride":2039,"cancel_ride":1800,"drvr_cancel":968,"rider_cancel":817,"earning":320622,"dist":16854.272,"avg_dist_pr_trip":8.2659,"avg_fare":157.2447,"srch_to_e_rate":0.9963,"e_to_q_srch_rate":0.4457,"q_accept_rate":0.5606,"q_to_bkng_rate":0.9969,"bkng_cancel_rate":0.4689,"cnvr_rate":0.1318},{"ward_num":"65","srch_fr_e":13854,"srch_which_got_e":13804,"srch_fr_q":6428,"srch_which_got_q":3210,"booking":3199,"ongng_ride":0,"done_ride":1713,"cancel_ride":1486,"drvr_cancel":786,"rider_cancel":691,"earning":267964,"dist":13783.424,"avg_dist_pr_trip":8.0464,"avg_fare":156.4297,"srch_to_e_rate":0.9964,"e_to_q_srch_rate":0.4657,"q_accept_rate":0.4994,"q_to_bkng_rate":0.9966,"bkng_cancel_rate":0.4645,"cnvr_rate":0.1236},{"ward_num":"66","srch_fr_e":13140,"srch_which_got_e":13097,"srch_fr_q":5801,"srch_which_got_q":3407,"booking":3397,"ongng_ride":0,"done_ride":1917,"cancel_ride":1480,"drvr_cancel":735,"rider_cancel":733,"earning":281953,"dist":14438.071,"avg_dist_pr_trip":7.5316,"avg_fare":147.0803,"srch_to_e_rate":0.9967,"e_to_q_srch_rate":0.4429,"q_accept_rate":0.5873,"q_to_bkng_rate":0.9971,"bkng_cancel_rate":0.4357,"cnvr_rate":0.1459},{"ward_num":"67","srch_fr_e":8755,"srch_which_got_e":8717,"srch_fr_q":4292,"srch_which_got_q":2377,"booking":2370,"ongng_ride":0,"done_ride":1340,"cancel_ride":1028,"drvr_cancel":549,"rider_cancel":474,"earning":197815,"dist":10256.095,"avg_dist_pr_trip":7.6538,"avg_fare":147.6231,"srch_to_e_rate":0.9957,"e_to_q_srch_rate":0.4924,"q_accept_rate":0.5538,"q_to_bkng_rate":0.9971,"bkng_cancel_rate":0.4338,"cnvr_rate":0.1531},{"ward_num":"68","srch_fr_e":8311,"srch_which_got_e":8283,"srch_fr_q":3468,"srch_which_got_q":2099,"booking":2092,"ongng_ride":0,"done_ride":1114,"cancel_ride":977,"drvr_cancel":555,"rider_cancel":417,"earning":171254,"dist":9119.102,"avg_dist_pr_trip":8.1859,"avg_fare":153.7289,"srch_to_e_rate":0.9966,"e_to_q_srch_rate":0.4187,"q_accept_rate":0.6052,"q_to_bkng_rate":0.9967,"bkng_cancel_rate":0.467,"cnvr_rate":0.134},{"ward_num":"69","srch_fr_e":12126,"srch_which_got_e":12073,"srch_fr_q":5524,"srch_which_got_q":3236,"booking":3232,"ongng_ride":0,"done_ride":1697,"cancel_ride":1535,"drvr_cancel":851,"rider_cancel":673,"earning":245592,"dist":12707.574,"avg_dist_pr_trip":7.4883,"avg_fare":144.7213,"srch_to_e_rate":0.9956,"e_to_q_srch_rate":0.4575,"q_accept_rate":0.5858,"q_to_bkng_rate":0.9988,"bkng_cancel_rate":0.4749,"cnvr_rate":0.1399},{"ward_num":"70","srch_fr_e":16835,"srch_which_got_e":16781,"srch_fr_q":8486,"srch_which_got_q":4476,"booking":4453,"ongng_ride":0,"done_ride":2470,"cancel_ride":1982,"drvr_cancel":1031,"rider_cancel":941,"earning":345302,"dist":17553.397,"avg_dist_pr_trip":7.1066,"avg_fare":139.7984,"srch_to_e_rate":0.9968,"e_to_q_srch_rate":0.5057,"q_accept_rate":0.5275,"q_to_bkng_rate":0.9949,"bkng_cancel_rate":0.4451,"cnvr_rate":0.1467},{"ward_num":"72","srch_fr_e":2558,"srch_which_got_e":2552,"srch_fr_q":1102,"srch_which_got_q":470,"booking":470,"ongng_ride":0,"done_ride":201,"cancel_ride":269,"drvr_cancel":141,"rider_cancel":125,"earning":31289,"dist":1665.451,"avg_dist_pr_trip":8.2858,"avg_fare":155.6667,"srch_to_e_rate":0.9977,"e_to_q_srch_rate":0.4318,"q_accept_rate":0.4265,"q_to_bkng_rate":1,"bkng_cancel_rate":0.5723,"cnvr_rate":0.0786},{"ward_num":"71","srch_fr_e":11166,"srch_which_got_e":11115,"srch_fr_q":5053,"srch_which_got_q":2331,"booking":2319,"ongng_ride":0,"done_ride":1274,"cancel_ride":1045,"drvr_cancel":571,"rider_cancel":465,"earning":186885,"dist":9656.986,"avg_dist_pr_trip":7.5801,"avg_fare":146.6915,"srch_to_e_rate":0.9954,"e_to_q_srch_rate":0.4546,"q_accept_rate":0.4613,"q_to_bkng_rate":0.9949,"bkng_cancel_rate":0.4506,"cnvr_rate":0.1141},{"ward_num":"73","srch_fr_e":4706,"srch_which_got_e":4668,"srch_fr_q":2115,"srch_which_got_q":1246,"booking":1243,"ongng_ride":0,"done_ride":613,"cancel_ride":629,"drvr_cancel":323,"rider_cancel":302,"earning":76181,"dist":3768.194,"avg_dist_pr_trip":6.1471,"avg_fare":124.2757,"srch_to_e_rate":0.9919,"e_to_q_srch_rate":0.4531,"q_accept_rate":0.5891,"q_to_bkng_rate":0.9976,"bkng_cancel_rate":0.506,"cnvr_rate":0.1303},{"ward_num":"74","srch_fr_e":8268,"srch_which_got_e":8244,"srch_fr_q":4124,"srch_which_got_q":2226,"booking":2222,"ongng_ride":0,"done_ride":1194,"cancel_ride":1028,"drvr_cancel":520,"rider_cancel":496,"earning":150271,"dist":7434.828,"avg_dist_pr_trip":6.2268,"avg_fare":125.8551,"srch_to_e_rate":0.9971,"e_to_q_srch_rate":0.5002,"q_accept_rate":0.5398,"q_to_bkng_rate":0.9982,"bkng_cancel_rate":0.4626,"cnvr_rate":0.1444},{"ward_num":"75","srch_fr_e":3157,"srch_which_got_e":3156,"srch_fr_q":1462,"srch_which_got_q":990,"booking":986,"ongng_ride":0,"done_ride":529,"cancel_ride":457,"drvr_cancel":258,"rider_cancel":198,"earning":83559,"dist":4421.825,"avg_dist_pr_trip":8.3588,"avg_fare":157.9565,"srch_to_e_rate":0.9997,"e_to_q_srch_rate":0.4632,"q_accept_rate":0.6772,"q_to_bkng_rate":0.996,"bkng_cancel_rate":0.4635,"cnvr_rate":0.1676},{"ward_num":"77","srch_fr_e":3456,"srch_which_got_e":3448,"srch_fr_q":1427,"srch_which_got_q":818,"booking":815,"ongng_ride":0,"done_ride":433,"cancel_ride":382,"drvr_cancel":190,"rider_cancel":190,"earning":58343,"dist":2897.781,"avg_dist_pr_trip":6.6923,"avg_fare":134.7413,"srch_to_e_rate":0.9977,"e_to_q_srch_rate":0.4139,"q_accept_rate":0.5732,"q_to_bkng_rate":0.9963,"bkng_cancel_rate":0.4687,"cnvr_rate":0.1253},{"ward_num":"76","srch_fr_e":7903,"srch_which_got_e":7886,"srch_fr_q":3859,"srch_which_got_q":2372,"booking":2365,"ongng_ride":0,"done_ride":1158,"cancel_ride":1204,"drvr_cancel":639,"rider_cancel":549,"earning":135752,"dist":6583.181,"avg_dist_pr_trip":5.685,"avg_fare":117.2297,"srch_to_e_rate":0.9978,"e_to_q_srch_rate":0.4893,"q_accept_rate":0.6147,"q_to_bkng_rate":0.997,"bkng_cancel_rate":0.5091,"cnvr_rate":0.1465},{"ward_num":"78","srch_fr_e":10308,"srch_which_got_e":10289,"srch_fr_q":5089,"srch_which_got_q":3480,"booking":3469,"ongng_ride":0,"done_ride":1893,"cancel_ride":1575,"drvr_cancel":788,"rider_cancel":779,"earning":221000,"dist":10610.046,"avg_dist_pr_trip":5.6049,"avg_fare":116.7459,"srch_to_e_rate":0.9982,"e_to_q_srch_rate":0.4946,"q_accept_rate":0.6838,"q_to_bkng_rate":0.9968,"bkng_cancel_rate":0.454,"cnvr_rate":0.1836},{"ward_num":"79","srch_fr_e":4679,"srch_which_got_e":4659,"srch_fr_q":1634,"srch_which_got_q":1005,"booking":1002,"ongng_ride":0,"done_ride":533,"cancel_ride":469,"drvr_cancel":266,"rider_cancel":200,"earning":99602,"dist":5356.405,"avg_dist_pr_trip":10.0495,"avg_fare":186.8705,"srch_to_e_rate":0.9957,"e_to_q_srch_rate":0.3507,"q_accept_rate":0.6151,"q_to_bkng_rate":0.997,"bkng_cancel_rate":0.4681,"cnvr_rate":0.1139},{"ward_num":"80","srch_fr_e":5214,"srch_which_got_e":5180,"srch_fr_q":1818,"srch_which_got_q":1257,"booking":1253,"ongng_ride":0,"done_ride":753,"cancel_ride":500,"drvr_cancel":237,"rider_cancel":257,"earning":123846,"dist":6457.683,"avg_dist_pr_trip":8.5759,"avg_fare":164.4701,"srch_to_e_rate":0.9935,"e_to_q_srch_rate":0.351,"q_accept_rate":0.6914,"q_to_bkng_rate":0.9968,"bkng_cancel_rate":0.399,"cnvr_rate":0.1444},{"ward_num":"81","srch_fr_e":9021,"srch_which_got_e":8987,"srch_fr_q":3186,"srch_which_got_q":2390,"booking":2369,"ongng_ride":0,"done_ride":1404,"cancel_ride":963,"drvr_cancel":501,"rider_cancel":457,"earning":214222,"dist":11007.018,"avg_dist_pr_trip":7.8398,"avg_fare":152.5798,"srch_to_e_rate":0.9962,"e_to_q_srch_rate":0.3545,"q_accept_rate":0.7502,"q_to_bkng_rate":0.9912,"bkng_cancel_rate":0.4065,"cnvr_rate":0.1556},{"ward_num":"82","srch_fr_e":10200,"srch_which_got_e":10165,"srch_fr_q":3650,"srch_which_got_q":1872,"booking":1862,"ongng_ride":0,"done_ride":1033,"cancel_ride":828,"drvr_cancel":422,"rider_cancel":403,"earning":189569,"dist":10030.738,"avg_dist_pr_trip":9.7103,"avg_fare":183.5131,"srch_to_e_rate":0.9966,"e_to_q_srch_rate":0.3591,"q_accept_rate":0.5129,"q_to_bkng_rate":0.9947,"bkng_cancel_rate":0.4447,"cnvr_rate":0.1013},{"ward_num":"83","srch_fr_e":15254,"srch_which_got_e":15166,"srch_fr_q":6987,"srch_which_got_q":2863,"booking":2855,"ongng_ride":0,"done_ride":1573,"cancel_ride":1281,"drvr_cancel":665,"rider_cancel":609,"earning":262981,"dist":13887.777,"avg_dist_pr_trip":8.8288,"avg_fare":167.1844,"srch_to_e_rate":0.9942,"e_to_q_srch_rate":0.4607,"q_accept_rate":0.4098,"q_to_bkng_rate":0.9972,"bkng_cancel_rate":0.4487,"cnvr_rate":0.1031},{"ward_num":"84","srch_fr_e":6177,"srch_which_got_e":6141,"srch_fr_q":2615,"srch_which_got_q":1300,"booking":1299,"ongng_ride":0,"done_ride":738,"cancel_ride":561,"drvr_cancel":299,"rider_cancel":262,"earning":117850,"dist":6197.886,"avg_dist_pr_trip":8.3982,"avg_fare":159.6883,"srch_to_e_rate":0.9942,"e_to_q_srch_rate":0.4258,"q_accept_rate":0.4971,"q_to_bkng_rate":0.9992,"bkng_cancel_rate":0.4319,"cnvr_rate":0.1195},{"ward_num":"85","srch_fr_e":6850,"srch_which_got_e":6816,"srch_fr_q":2419,"srch_which_got_q":1143,"booking":1142,"ongng_ride":0,"done_ride":627,"cancel_ride":515,"drvr_cancel":278,"rider_cancel":235,"earning":106639,"dist":5556.094,"avg_dist_pr_trip":8.8614,"avg_fare":170.0781,"srch_to_e_rate":0.995,"e_to_q_srch_rate":0.3549,"q_accept_rate":0.4725,"q_to_bkng_rate":0.9991,"bkng_cancel_rate":0.451,"cnvr_rate":0.0915},{"ward_num":"86","srch_fr_e":13662,"srch_which_got_e":13560,"srch_fr_q":5895,"srch_which_got_q":2627,"booking":2617,"ongng_ride":0,"done_ride":1398,"cancel_ride":1219,"drvr_cancel":625,"rider_cancel":589,"earning":225493,"dist":11709.15,"avg_dist_pr_trip":8.3756,"avg_fare":161.2969,"srch_to_e_rate":0.9925,"e_to_q_srch_rate":0.4347,"q_accept_rate":0.4456,"q_to_bkng_rate":0.9962,"bkng_cancel_rate":0.4658,"cnvr_rate":0.1023},{"ward_num":"87","srch_fr_e":4178,"srch_which_got_e":4161,"srch_fr_q":1668,"srch_which_got_q":999,"booking":995,"ongng_ride":0,"done_ride":495,"cancel_ride":500,"drvr_cancel":264,"rider_cancel":230,"earning":65449,"dist":3163.941,"avg_dist_pr_trip":6.3918,"avg_fare":132.2202,"srch_to_e_rate":0.9959,"e_to_q_srch_rate":0.4009,"q_accept_rate":0.5989,"q_to_bkng_rate":0.996,"bkng_cancel_rate":0.5025,"cnvr_rate":0.1185},{"ward_num":"88","srch_fr_e":9930,"srch_which_got_e":9908,"srch_fr_q":5235,"srch_which_got_q":3061,"booking":3049,"ongng_ride":0,"done_ride":1822,"cancel_ride":1225,"drvr_cancel":689,"rider_cancel":528,"earning":241743,"dist":11815.891,"avg_dist_pr_trip":6.4851,"avg_fare":132.68,"srch_to_e_rate":0.9978,"e_to_q_srch_rate":0.5284,"q_accept_rate":0.5847,"q_to_bkng_rate":0.9961,"bkng_cancel_rate":0.4018,"cnvr_rate":0.1835},{"ward_num":"89","srch_fr_e":7744,"srch_which_got_e":7721,"srch_fr_q":3657,"srch_which_got_q":2304,"booking":2299,"ongng_ride":0,"done_ride":1345,"cancel_ride":953,"drvr_cancel":489,"rider_cancel":455,"earning":185164,"dist":9041.935,"avg_dist_pr_trip":6.7226,"avg_fare":137.6684,"srch_to_e_rate":0.997,"e_to_q_srch_rate":0.4736,"q_accept_rate":0.63,"q_to_bkng_rate":0.9978,"bkng_cancel_rate":0.4145,"cnvr_rate":0.1737},{"ward_num":"90","srch_fr_e":14110,"srch_which_got_e":14046,"srch_fr_q":6844,"srch_which_got_q":4293,"booking":4283,"ongng_ride":0,"done_ride":2310,"cancel_ride":1972,"drvr_cancel":1065,"rider_cancel":898,"earning":315781,"dist":15635.481,"avg_dist_pr_trip":6.7686,"avg_fare":136.7017,"srch_to_e_rate":0.9955,"e_to_q_srch_rate":0.4873,"q_accept_rate":0.6273,"q_to_bkng_rate":0.9977,"bkng_cancel_rate":0.4604,"cnvr_rate":0.1637},{"ward_num":"91","srch_fr_e":10243,"srch_which_got_e":10214,"srch_fr_q":4763,"srch_which_got_q":2902,"booking":2894,"ongng_ride":0,"done_ride":1648,"cancel_ride":1246,"drvr_cancel":651,"rider_cancel":590,"earning":238133,"dist":11873.36,"avg_dist_pr_trip":7.2047,"avg_fare":144.4982,"srch_to_e_rate":0.9972,"e_to_q_srch_rate":0.4663,"q_accept_rate":0.6093,"q_to_bkng_rate":0.9972,"bkng_cancel_rate":0.4305,"cnvr_rate":0.1609},{"ward_num":"92","srch_fr_e":10741,"srch_which_got_e":10714,"srch_fr_q":5065,"srch_which_got_q":3174,"booking":3160,"ongng_ride":0,"done_ride":1892,"cancel_ride":1268,"drvr_cancel":682,"rider_cancel":577,"earning":268307,"dist":13375.202,"avg_dist_pr_trip":7.0693,"avg_fare":141.8113,"srch_to_e_rate":0.9975,"e_to_q_srch_rate":0.4727,"q_accept_rate":0.6267,"q_to_bkng_rate":0.9956,"bkng_cancel_rate":0.4013,"cnvr_rate":0.1761},{"ward_num":"93","srch_fr_e":12538,"srch_which_got_e":12504,"srch_fr_q":6205,"srch_which_got_q":3152,"booking":3146,"ongng_ride":0,"done_ride":1812,"cancel_ride":1334,"drvr_cancel":713,"rider_cancel":616,"earning":255134,"dist":12570.914,"avg_dist_pr_trip":6.9376,"avg_fare":140.8024,"srch_to_e_rate":0.9973,"e_to_q_srch_rate":0.4962,"q_accept_rate":0.508,"q_to_bkng_rate":0.9981,"bkng_cancel_rate":0.424,"cnvr_rate":0.1445},{"ward_num":"94","srch_fr_e":12063,"srch_which_got_e":12034,"srch_fr_q":5384,"srch_which_got_q":2755,"booking":2745,"ongng_ride":0,"done_ride":1441,"cancel_ride":1304,"drvr_cancel":667,"rider_cancel":632,"earning":210615,"dist":10634.614,"avg_dist_pr_trip":7.38,"avg_fare":146.1589,"srch_to_e_rate":0.9976,"e_to_q_srch_rate":0.4474,"q_accept_rate":0.5117,"q_to_bkng_rate":0.9964,"bkng_cancel_rate":0.475,"cnvr_rate":0.1195},{"ward_num":"95","srch_fr_e":18357,"srch_which_got_e":18311,"srch_fr_q":8349,"srch_which_got_q":4786,"booking":4771,"ongng_ride":0,"done_ride":2821,"cancel_ride":1950,"drvr_cancel":1028,"rider_cancel":916,"earning":367070,"dist":18155.351,"avg_dist_pr_trip":6.4358,"avg_fare":130.1205,"srch_to_e_rate":0.9975,"e_to_q_srch_rate":0.456,"q_accept_rate":0.5732,"q_to_bkng_rate":0.9969,"bkng_cancel_rate":0.4087,"cnvr_rate":0.1537},{"ward_num":"96","srch_fr_e":9508,"srch_which_got_e":9481,"srch_fr_q":4340,"srch_which_got_q":2347,"booking":2340,"ongng_ride":0,"done_ride":1285,"cancel_ride":1055,"drvr_cancel":575,"rider_cancel":472,"earning":182104,"dist":9229.905,"avg_dist_pr_trip":7.1828,"avg_fare":141.7152,"srch_to_e_rate":0.9972,"e_to_q_srch_rate":0.4578,"q_accept_rate":0.5408,"q_to_bkng_rate":0.997,"bkng_cancel_rate":0.4509,"cnvr_rate":0.1351},{"ward_num":"97","srch_fr_e":9699,"srch_which_got_e":9688,"srch_fr_q":4864,"srch_which_got_q":2613,"booking":2608,"ongng_ride":0,"done_ride":1458,"cancel_ride":1150,"drvr_cancel":635,"rider_cancel":509,"earning":183796,"dist":9035.795,"avg_dist_pr_trip":6.1974,"avg_fare":126.0604,"srch_to_e_rate":0.9989,"e_to_q_srch_rate":0.5021,"q_accept_rate":0.5372,"q_to_bkng_rate":0.9981,"bkng_cancel_rate":0.441,"cnvr_rate":0.1503},{"ward_num":"98","srch_fr_e":6956,"srch_which_got_e":6939,"srch_fr_q":3656,"srch_which_got_q":2007,"booking":2003,"ongng_ride":0,"done_ride":1141,"cancel_ride":862,"drvr_cancel":469,"rider_cancel":386,"earning":153547,"dist":7665.893,"avg_dist_pr_trip":6.7186,"avg_fare":134.5723,"srch_to_e_rate":0.9976,"e_to_q_srch_rate":0.5269,"q_accept_rate":0.549,"q_to_bkng_rate":0.998,"bkng_cancel_rate":0.4304,"cnvr_rate":0.164},{"ward_num":"99","srch_fr_e":28067,"srch_which_got_e":27988,"srch_fr_q":15815,"srch_which_got_q":10476,"booking":10445,"ongng_ride":0,"done_ride":6195,"cancel_ride":4246,"drvr_cancel":2246,"rider_cancel":1981,"earning":745671,"dist":35489.511,"avg_dist_pr_trip":5.7287,"avg_fare":120.3666,"srch_to_e_rate":0.9972,"e_to_q_srch_rate":0.5651,"q_accept_rate":0.6624,"q_to_bkng_rate":0.997,"bkng_cancel_rate":0.4065,"cnvr_rate":0.2207},{"ward_num":"100","srch_fr_e":26611,"srch_which_got_e":26554,"srch_fr_q":14818,"srch_which_got_q":9489,"booking":9461,"ongng_ride":0,"done_ride":5721,"cancel_ride":3739,"drvr_cancel":1950,"rider_cancel":1767,"earning":677200,"dist":32168.331,"avg_dist_pr_trip":5.6229,"avg_fare":118.3709,"srch_to_e_rate":0.9979,"e_to_q_srch_rate":0.558,"q_accept_rate":0.6404,"q_to_bkng_rate":0.997,"bkng_cancel_rate":0.3952,"cnvr_rate":0.215},{"ward_num":"101","srch_fr_e":18343,"srch_which_got_e":18277,"srch_fr_q":10366,"srch_which_got_q":6499,"booking":6481,"ongng_ride":0,"done_ride":3705,"cancel_ride":2775,"drvr_cancel":1411,"rider_cancel":1343,"earning":450640,"dist":21664.892,"avg_dist_pr_trip":5.8475,"avg_fare":121.6302,"srch_to_e_rate":0.9964,"e_to_q_srch_rate":0.5672,"q_accept_rate":0.627,"q_to_bkng_rate":0.9972,"bkng_cancel_rate":0.4282,"cnvr_rate":0.202},{"ward_num":"102","srch_fr_e":16457,"srch_which_got_e":16400,"srch_fr_q":8650,"srch_which_got_q":5300,"booking":5283,"ongng_ride":0,"done_ride":3156,"cancel_ride":2126,"drvr_cancel":1069,"rider_cancel":1045,"earning":368354,"dist":17388.934,"avg_dist_pr_trip":5.5098,"avg_fare":116.7155,"srch_to_e_rate":0.9965,"e_to_q_srch_rate":0.5274,"q_accept_rate":0.6127,"q_to_bkng_rate":0.9968,"bkng_cancel_rate":0.4024,"cnvr_rate":0.1918},{"ward_num":"103","srch_fr_e":25449,"srch_which_got_e":25366,"srch_fr_q":14570,"srch_which_got_q":8501,"booking":8477,"ongng_ride":0,"done_ride":4597,"cancel_ride":3878,"drvr_cancel":1962,"rider_cancel":1887,"earning":534541,"dist":25333.793,"avg_dist_pr_trip":5.5109,"avg_fare":116.2804,"srch_to_e_rate":0.9967,"e_to_q_srch_rate":0.5744,"q_accept_rate":0.5835,"q_to_bkng_rate":0.9972,"bkng_cancel_rate":0.4575,"cnvr_rate":0.1806},{"ward_num":"104","srch_fr_e":18399,"srch_which_got_e":18354,"srch_fr_q":9417,"srch_which_got_q":6438,"booking":6422,"ongng_ride":0,"done_ride":3467,"cancel_ride":2955,"drvr_cancel":1489,"rider_cancel":1449,"earning":407974,"dist":19638.34,"avg_dist_pr_trip":5.6644,"avg_fare":117.6735,"srch_to_e_rate":0.9976,"e_to_q_srch_rate":0.5131,"q_accept_rate":0.6837,"q_to_bkng_rate":0.9975,"bkng_cancel_rate":0.4601,"cnvr_rate":0.1884},{"ward_num":"105","srch_fr_e":16750,"srch_which_got_e":16696,"srch_fr_q":7727,"srch_which_got_q":4464,"booking":4451,"ongng_ride":0,"done_ride":2215,"cancel_ride":2236,"drvr_cancel":1079,"rider_cancel":1145,"earning":325241,"dist":16437.167,"avg_dist_pr_trip":7.4208,"avg_fare":146.8357,"srch_to_e_rate":0.9968,"e_to_q_srch_rate":0.4628,"q_accept_rate":0.5777,"q_to_bkng_rate":0.9971,"bkng_cancel_rate":0.5024,"cnvr_rate":0.1322},{"ward_num":"106","srch_fr_e":14744,"srch_which_got_e":14711,"srch_fr_q":8003,"srch_which_got_q":4222,"booking":4208,"ongng_ride":0,"done_ride":2172,"cancel_ride":2036,"drvr_cancel":979,"rider_cancel":1047,"earning":288551,"dist":13981.909,"avg_dist_pr_trip":6.4373,"avg_fare":132.8504,"srch_to_e_rate":0.9978,"e_to_q_srch_rate":0.544,"q_accept_rate":0.5276,"q_to_bkng_rate":0.9967,"bkng_cancel_rate":0.4838,"cnvr_rate":0.1473},{"ward_num":"107","srch_fr_e":13055,"srch_which_got_e":13008,"srch_fr_q":7023,"srch_which_got_q":3457,"booking":3448,"ongng_ride":0,"done_ride":1850,"cancel_ride":1597,"drvr_cancel":851,"rider_cancel":739,"earning":238287,"dist":11712.221,"avg_dist_pr_trip":6.3309,"avg_fare":128.8038,"srch_to_e_rate":0.9964,"e_to_q_srch_rate":0.5399,"q_accept_rate":0.4922,"q_to_bkng_rate":0.9974,"bkng_cancel_rate":0.4632,"cnvr_rate":0.1417},{"ward_num":"108","srch_fr_e":13711,"srch_which_got_e":13674,"srch_fr_q":6952,"srch_which_got_q":3305,"booking":3289,"ongng_ride":0,"done_ride":1565,"cancel_ride":1724,"drvr_cancel":879,"rider_cancel":839,"earning":212565,"dist":10322.293,"avg_dist_pr_trip":6.5957,"avg_fare":135.8243,"srch_to_e_rate":0.9973,"e_to_q_srch_rate":0.5084,"q_accept_rate":0.4754,"q_to_bkng_rate":0.9952,"bkng_cancel_rate":0.5242,"cnvr_rate":0.1141},{"ward_num":"109","srch_fr_e":13238,"srch_which_got_e":13222,"srch_fr_q":7025,"srch_which_got_q":3446,"booking":3436,"ongng_ride":0,"done_ride":1837,"cancel_ride":1599,"drvr_cancel":755,"rider_cancel":831,"earning":243076,"dist":11901.927,"avg_dist_pr_trip":6.479,"avg_fare":132.3223,"srch_to_e_rate":0.9988,"e_to_q_srch_rate":0.5313,"q_accept_rate":0.4905,"q_to_bkng_rate":0.9971,"bkng_cancel_rate":0.4654,"cnvr_rate":0.1388},{"ward_num":"110","srch_fr_e":23368,"srch_which_got_e":23282,"srch_fr_q":13166,"srch_which_got_q":6388,"booking":6372,"ongng_ride":0,"done_ride":3394,"cancel_ride":2976,"drvr_cancel":1505,"rider_cancel":1449,"earning":426455,"dist":20492.604,"avg_dist_pr_trip":6.0379,"avg_fare":125.6497,"srch_to_e_rate":0.9963,"e_to_q_srch_rate":0.5655,"q_accept_rate":0.4852,"q_to_bkng_rate":0.9975,"bkng_cancel_rate":0.467,"cnvr_rate":0.1452},{"ward_num":"111","srch_fr_e":55256,"srch_which_got_e":55097,"srch_fr_q":34343,"srch_which_got_q":17638,"booking":17593,"ongng_ride":0,"done_ride":8677,"cancel_ride":8911,"drvr_cancel":4366,"rider_cancel":4485,"earning":1176843,"dist":57386.297,"avg_dist_pr_trip":6.6136,"avg_fare":135.6279,"srch_to_e_rate":0.9971,"e_to_q_srch_rate":0.6233,"q_accept_rate":0.5136,"q_to_bkng_rate":0.9974,"bkng_cancel_rate":0.5065,"cnvr_rate":0.157},{"ward_num":"112","srch_fr_e":14566,"srch_which_got_e":14501,"srch_fr_q":7534,"srch_which_got_q":3553,"booking":3548,"ongng_ride":0,"done_ride":1910,"cancel_ride":1635,"drvr_cancel":844,"rider_cancel":780,"earning":248115,"dist":11897.525,"avg_dist_pr_trip":6.2291,"avg_fare":129.9031,"srch_to_e_rate":0.9955,"e_to_q_srch_rate":0.5196,"q_accept_rate":0.4716,"q_to_bkng_rate":0.9986,"bkng_cancel_rate":0.4608,"cnvr_rate":0.1311},{"ward_num":"113","srch_fr_e":27770,"srch_which_got_e":27719,"srch_fr_q":16999,"srch_which_got_q":8747,"booking":8720,"ongng_ride":0,"done_ride":4373,"cancel_ride":4346,"drvr_cancel":2179,"rider_cancel":2132,"earning":589486,"dist":28309.271,"avg_dist_pr_trip":6.4736,"avg_fare":134.8013,"srch_to_e_rate":0.9982,"e_to_q_srch_rate":0.6133,"q_accept_rate":0.5146,"q_to_bkng_rate":0.9969,"bkng_cancel_rate":0.4984,"cnvr_rate":0.1575},{"ward_num":"114","srch_fr_e":20936,"srch_which_got_e":20873,"srch_fr_q":11019,"srch_which_got_q":5755,"booking":5731,"ongng_ride":0,"done_ride":2805,"cancel_ride":2926,"drvr_cancel":1475,"rider_cancel":1411,"earning":405137,"dist":19899.941,"avg_dist_pr_trip":7.0945,"avg_fare":144.4339,"srch_to_e_rate":0.997,"e_to_q_srch_rate":0.5279,"q_accept_rate":0.5223,"q_to_bkng_rate":0.9958,"bkng_cancel_rate":0.5106,"cnvr_rate":0.134},{"ward_num":"115","srch_fr_e":12787,"srch_which_got_e":12757,"srch_fr_q":6449,"srch_which_got_q":4146,"booking":4134,"ongng_ride":0,"done_ride":2171,"cancel_ride":1963,"drvr_cancel":1056,"rider_cancel":889,"earning":284708,"dist":14255.86,"avg_dist_pr_trip":6.5665,"avg_fare":131.1414,"srch_to_e_rate":0.9977,"e_to_q_srch_rate":0.5055,"q_accept_rate":0.6429,"q_to_bkng_rate":0.9971,"bkng_cancel_rate":0.4748,"cnvr_rate":0.1698},{"ward_num":"116","srch_fr_e":11553,"srch_which_got_e":11518,"srch_fr_q":5697,"srch_which_got_q":3689,"booking":3678,"ongng_ride":0,"done_ride":2078,"cancel_ride":1600,"drvr_cancel":842,"rider_cancel":745,"earning":303736,"dist":15453.586,"avg_dist_pr_trip":7.4368,"avg_fare":146.1675,"srch_to_e_rate":0.997,"e_to_q_srch_rate":0.4946,"q_accept_rate":0.6475,"q_to_bkng_rate":0.997,"bkng_cancel_rate":0.435,"cnvr_rate":0.1799},{"ward_num":"117","srch_fr_e":26957,"srch_which_got_e":26904,"srch_fr_q":15992,"srch_which_got_q":9030,"booking":9001,"ongng_ride":0,"done_ride":5073,"cancel_ride":3926,"drvr_cancel":1929,"rider_cancel":1969,"earning":625887,"dist":29515.148,"avg_dist_pr_trip":5.8181,"avg_fare":123.3761,"srch_to_e_rate":0.998,"e_to_q_srch_rate":0.5944,"q_accept_rate":0.5647,"q_to_bkng_rate":0.9968,"bkng_cancel_rate":0.4362,"cnvr_rate":0.1882},{"ward_num":"118","srch_fr_e":26338,"srch_which_got_e":26261,"srch_fr_q":15742,"srch_which_got_q":8236,"booking":8219,"ongng_ride":0,"done_ride":4333,"cancel_ride":3884,"drvr_cancel":1936,"rider_cancel":1923,"earning":532475,"dist":25633.725,"avg_dist_pr_trip":5.9159,"avg_fare":122.8883,"srch_to_e_rate":0.9971,"e_to_q_srch_rate":0.5994,"q_accept_rate":0.5232,"q_to_bkng_rate":0.9979,"bkng_cancel_rate":0.4726,"cnvr_rate":0.1645},{"ward_num":"119","srch_fr_e":21528,"srch_which_got_e":21458,"srch_fr_q":11914,"srch_which_got_q":7283,"booking":7257,"ongng_ride":0,"done_ride":4011,"cancel_ride":3244,"drvr_cancel":1663,"rider_cancel":1565,"earning":517026,"dist":25438.359,"avg_dist_pr_trip":6.3421,"avg_fare":128.902,"srch_to_e_rate":0.9967,"e_to_q_srch_rate":0.5552,"q_accept_rate":0.6113,"q_to_bkng_rate":0.9964,"bkng_cancel_rate":0.447,"cnvr_rate":0.1863},{"ward_num":"120","srch_fr_e":6903,"srch_which_got_e":6888,"srch_fr_q":3487,"srch_which_got_q":1833,"booking":1822,"ongng_ride":0,"done_ride":965,"cancel_ride":857,"drvr_cancel":441,"rider_cancel":407,"earning":141686,"dist":7083.713,"avg_dist_pr_trip":7.3406,"avg_fare":146.8249,"srch_to_e_rate":0.9978,"e_to_q_srch_rate":0.5062,"q_accept_rate":0.5257,"q_to_bkng_rate":0.994,"bkng_cancel_rate":0.4704,"cnvr_rate":0.1398},{"ward_num":"121","srch_fr_e":10615,"srch_which_got_e":10560,"srch_fr_q":5888,"srch_which_got_q":3112,"booking":3106,"ongng_ride":0,"done_ride":1673,"cancel_ride":1433,"drvr_cancel":669,"rider_cancel":757,"earning":235204,"dist":11530.591,"avg_dist_pr_trip":6.8922,"avg_fare":140.5882,"srch_to_e_rate":0.9948,"e_to_q_srch_rate":0.5576,"q_accept_rate":0.5285,"q_to_bkng_rate":0.9981,"bkng_cancel_rate":0.4614,"cnvr_rate":0.1576},{"ward_num":"122","srch_fr_e":17943,"srch_which_got_e":17907,"srch_fr_q":10407,"srch_which_got_q":4895,"booking":4883,"ongng_ride":0,"done_ride":2587,"cancel_ride":2296,"drvr_cancel":1135,"rider_cancel":1147,"earning":343516,"dist":16564.902,"avg_dist_pr_trip":6.4031,"avg_fare":132.7855,"srch_to_e_rate":0.998,"e_to_q_srch_rate":0.5812,"q_accept_rate":0.4704,"q_to_bkng_rate":0.9975,"bkng_cancel_rate":0.4702,"cnvr_rate":0.1442},{"ward_num":"123","srch_fr_e":30685,"srch_which_got_e":30616,"srch_fr_q":17914,"srch_which_got_q":10703,"booking":10671,"ongng_ride":0,"done_ride":6162,"cancel_ride":4503,"drvr_cancel":2184,"rider_cancel":2289,"earning":768331,"dist":36966.948,"avg_dist_pr_trip":5.9992,"avg_fare":124.6886,"srch_to_e_rate":0.9978,"e_to_q_srch_rate":0.5851,"q_accept_rate":0.5975,"q_to_bkng_rate":0.997,"bkng_cancel_rate":0.422,"cnvr_rate":0.2008},{"ward_num":"124","srch_fr_e":17214,"srch_which_got_e":17179,"srch_fr_q":9194,"srch_which_got_q":6139,"booking":6122,"ongng_ride":0,"done_ride":3177,"cancel_ride":2945,"drvr_cancel":1559,"rider_cancel":1359,"earning":444283,"dist":22446.876,"avg_dist_pr_trip":7.0654,"avg_fare":139.8436,"srch_to_e_rate":0.998,"e_to_q_srch_rate":0.5352,"q_accept_rate":0.6677,"q_to_bkng_rate":0.9972,"bkng_cancel_rate":0.4811,"cnvr_rate":0.1846},{"ward_num":"125","srch_fr_e":13232,"srch_which_got_e":13201,"srch_fr_q":6784,"srch_which_got_q":3849,"booking":3838,"ongng_ride":0,"done_ride":1970,"cancel_ride":1867,"drvr_cancel":984,"rider_cancel":865,"earning":302285,"dist":15428.744,"avg_dist_pr_trip":7.8318,"avg_fare":153.4442,"srch_to_e_rate":0.9977,"e_to_q_srch_rate":0.5139,"q_accept_rate":0.5674,"q_to_bkng_rate":0.9971,"bkng_cancel_rate":0.4865,"cnvr_rate":0.1489},{"ward_num":"126","srch_fr_e":11120,"srch_which_got_e":11086,"srch_fr_q":5549,"srch_which_got_q":3490,"booking":3480,"ongng_ride":0,"done_ride":1950,"cancel_ride":1529,"drvr_cancel":795,"rider_cancel":728,"earning":260276,"dist":12885.102,"avg_dist_pr_trip":6.6077,"avg_fare":133.4749,"srch_to_e_rate":0.9969,"e_to_q_srch_rate":0.5005,"q_accept_rate":0.6289,"q_to_bkng_rate":0.9971,"bkng_cancel_rate":0.4394,"cnvr_rate":0.1754},{"ward_num":"127","srch_fr_e":43607,"srch_which_got_e":43379,"srch_fr_q":19034,"srch_which_got_q":10658,"booking":10605,"ongng_ride":0,"done_ride":5844,"cancel_ride":4757,"drvr_cancel":2435,"rider_cancel":2290,"earning":876034,"dist":43915.559,"avg_dist_pr_trip":7.5146,"avg_fare":149.9031,"srch_to_e_rate":0.9948,"e_to_q_srch_rate":0.4388,"q_accept_rate":0.5599,"q_to_bkng_rate":0.995,"bkng_cancel_rate":0.4486,"cnvr_rate":0.134},{"ward_num":"128","srch_fr_e":25451,"srch_which_got_e":25395,"srch_fr_q":13828,"srch_which_got_q":6726,"booking":6709,"ongng_ride":0,"done_ride":3568,"cancel_ride":3139,"drvr_cancel":1753,"rider_cancel":1367,"earning":516652,"dist":25382.572,"avg_dist_pr_trip":7.1139,"avg_fare":144.8016,"srch_to_e_rate":0.9978,"e_to_q_srch_rate":0.5445,"q_accept_rate":0.4864,"q_to_bkng_rate":0.9975,"bkng_cancel_rate":0.4679,"cnvr_rate":0.1402},{"ward_num":"129","srch_fr_e":23920,"srch_which_got_e":23870,"srch_fr_q":13018,"srch_which_got_q":6861,"booking":6835,"ongng_ride":0,"done_ride":3947,"cancel_ride":2883,"drvr_cancel":1548,"rider_cancel":1317,"earning":551703,"dist":26705.525,"avg_dist_pr_trip":6.766,"avg_fare":139.7778,"srch_to_e_rate":0.9979,"e_to_q_srch_rate":0.5454,"q_accept_rate":0.527,"q_to_bkng_rate":0.9962,"bkng_cancel_rate":0.4218,"cnvr_rate":0.165},{"ward_num":"130","srch_fr_e":28110,"srch_which_got_e":28057,"srch_fr_q":15696,"srch_which_got_q":8455,"booking":8440,"ongng_ride":0,"done_ride":4537,"cancel_ride":3901,"drvr_cancel":2073,"rider_cancel":1798,"earning":621533,"dist":29956.206,"avg_dist_pr_trip":6.6026,"avg_fare":136.9921,"srch_to_e_rate":0.9981,"e_to_q_srch_rate":0.5594,"q_accept_rate":0.5387,"q_to_bkng_rate":0.9982,"bkng_cancel_rate":0.4622,"cnvr_rate":0.1614},{"ward_num":"131","srch_fr_e":12968,"srch_which_got_e":12940,"srch_fr_q":6818,"srch_which_got_q":3858,"booking":3851,"ongng_ride":0,"done_ride":2163,"cancel_ride":1686,"drvr_cancel":885,"rider_cancel":787,"earning":306198,"dist":14940.029,"avg_dist_pr_trip":6.9071,"avg_fare":141.5617,"srch_to_e_rate":0.9978,"e_to_q_srch_rate":0.5269,"q_accept_rate":0.5659,"q_to_bkng_rate":0.9982,"bkng_cancel_rate":0.4378,"cnvr_rate":0.1668},{"ward_num":"132","srch_fr_e":20740,"srch_which_got_e":20678,"srch_fr_q":11915,"srch_which_got_q":7077,"booking":7058,"ongng_ride":0,"done_ride":3997,"cancel_ride":3059,"drvr_cancel":1567,"rider_cancel":1472,"earning":484867,"dist":22712.294,"avg_dist_pr_trip":5.6823,"avg_fare":121.3077,"srch_to_e_rate":0.997,"e_to_q_srch_rate":0.5762,"q_accept_rate":0.594,"q_to_bkng_rate":0.9973,"bkng_cancel_rate":0.4334,"cnvr_rate":0.1927},{"ward_num":"133","srch_fr_e":15271,"srch_which_got_e":15239,"srch_fr_q":8456,"srch_which_got_q":4799,"booking":4786,"ongng_ride":0,"done_ride":2753,"cancel_ride":2030,"drvr_cancel":1065,"rider_cancel":950,"earning":356036,"dist":16687.939,"avg_dist_pr_trip":6.0617,"avg_fare":129.3266,"srch_to_e_rate":0.9979,"e_to_q_srch_rate":0.5549,"q_accept_rate":0.5675,"q_to_bkng_rate":0.9973,"bkng_cancel_rate":0.4242,"cnvr_rate":0.1803},{"ward_num":"134","srch_fr_e":17344,"srch_which_got_e":17314,"srch_fr_q":9634,"srch_which_got_q":5001,"booking":4980,"ongng_ride":0,"done_ride":2845,"cancel_ride":2132,"drvr_cancel":1088,"rider_cancel":1037,"earning":362910,"dist":17161.363,"avg_dist_pr_trip":6.0321,"avg_fare":127.5606,"srch_to_e_rate":0.9983,"e_to_q_srch_rate":0.5564,"q_accept_rate":0.5191,"q_to_bkng_rate":0.9958,"bkng_cancel_rate":0.4281,"cnvr_rate":0.164},{"ward_num":"135","srch_fr_e":18526,"srch_which_got_e":18481,"srch_fr_q":10594,"srch_which_got_q":5869,"booking":5846,"ongng_ride":0,"done_ride":3620,"cancel_ride":2225,"drvr_cancel":1188,"rider_cancel":1030,"earning":446822,"dist":21166.343,"avg_dist_pr_trip":5.8471,"avg_fare":123.4315,"srch_to_e_rate":0.9976,"e_to_q_srch_rate":0.5732,"q_accept_rate":0.554,"q_to_bkng_rate":0.9961,"bkng_cancel_rate":0.3806,"cnvr_rate":0.1954},{"ward_num":"136","srch_fr_e":48544,"srch_which_got_e":48471,"srch_fr_q":31813,"srch_which_got_q":17333,"booking":17298,"ongng_ride":0,"done_ride":9126,"cancel_ride":8170,"drvr_cancel":4255,"rider_cancel":3850,"earning":1223730,"dist":58989.373,"avg_dist_pr_trip":6.4639,"avg_fare":134.0927,"srch_to_e_rate":0.9985,"e_to_q_srch_rate":0.6563,"q_accept_rate":0.5448,"q_to_bkng_rate":0.998,"bkng_cancel_rate":0.4723,"cnvr_rate":0.188},{"ward_num":"137","srch_fr_e":13504,"srch_which_got_e":13473,"srch_fr_q":6841,"srch_which_got_q":3761,"booking":3753,"ongng_ride":0,"done_ride":2106,"cancel_ride":1645,"drvr_cancel":825,"rider_cancel":810,"earning":281662,"dist":13812.557,"avg_dist_pr_trip":6.5587,"avg_fare":133.7426,"srch_to_e_rate":0.9977,"e_to_q_srch_rate":0.5078,"q_accept_rate":0.5498,"q_to_bkng_rate":0.9979,"bkng_cancel_rate":0.4383,"cnvr_rate":0.156},{"ward_num":"138","srch_fr_e":12376,"srch_which_got_e":12323,"srch_fr_q":6082,"srch_which_got_q":3405,"booking":3394,"ongng_ride":0,"done_ride":1896,"cancel_ride":1497,"drvr_cancel":754,"rider_cancel":737,"earning":264447,"dist":13309.25,"avg_dist_pr_trip":7.0196,"avg_fare":139.4763,"srch_to_e_rate":0.9957,"e_to_q_srch_rate":0.4935,"q_accept_rate":0.5598,"q_to_bkng_rate":0.9968,"bkng_cancel_rate":0.4411,"cnvr_rate":0.1532},{"ward_num":"139","srch_fr_e":8024,"srch_which_got_e":8001,"srch_fr_q":3882,"srch_which_got_q":2243,"booking":2238,"ongng_ride":0,"done_ride":1236,"cancel_ride":1001,"drvr_cancel":521,"rider_cancel":476,"earning":159282,"dist":7670.772,"avg_dist_pr_trip":6.2061,"avg_fare":128.8689,"srch_to_e_rate":0.9971,"e_to_q_srch_rate":0.4852,"q_accept_rate":0.5778,"q_to_bkng_rate":0.9978,"bkng_cancel_rate":0.4473,"cnvr_rate":0.154},{"ward_num":"140","srch_fr_e":9058,"srch_which_got_e":9035,"srch_fr_q":4350,"srch_which_got_q":2626,"booking":2624,"ongng_ride":0,"done_ride":1465,"cancel_ride":1159,"drvr_cancel":590,"rider_cancel":561,"earning":195488,"dist":9452.565,"avg_dist_pr_trip":6.4523,"avg_fare":133.4389,"srch_to_e_rate":0.9975,"e_to_q_srch_rate":0.4815,"q_accept_rate":0.6037,"q_to_bkng_rate":0.9992,"bkng_cancel_rate":0.4417,"cnvr_rate":0.1617},{"ward_num":"141","srch_fr_e":17780,"srch_which_got_e":17691,"srch_fr_q":9457,"srch_which_got_q":5369,"booking":5350,"ongng_ride":0,"done_ride":2818,"cancel_ride":2529,"drvr_cancel":1268,"rider_cancel":1238,"earning":361452,"dist":17698.206,"avg_dist_pr_trip":6.2804,"avg_fare":128.2654,"srch_to_e_rate":0.995,"e_to_q_srch_rate":0.5346,"q_accept_rate":0.5677,"q_to_bkng_rate":0.9965,"bkng_cancel_rate":0.4727,"cnvr_rate":0.1585},{"ward_num":"142","srch_fr_e":14478,"srch_which_got_e":14445,"srch_fr_q":7112,"srch_which_got_q":3946,"booking":3937,"ongng_ride":0,"done_ride":2148,"cancel_ride":1788,"drvr_cancel":932,"rider_cancel":844,"earning":286463,"dist":13958.992,"avg_dist_pr_trip":6.4986,"avg_fare":133.3627,"srch_to_e_rate":0.9977,"e_to_q_srch_rate":0.4924,"q_accept_rate":0.5548,"q_to_bkng_rate":0.9977,"bkng_cancel_rate":0.4542,"cnvr_rate":0.1484},{"ward_num":"143","srch_fr_e":12509,"srch_which_got_e":12438,"srch_fr_q":6265,"srch_which_got_q":2998,"booking":2992,"ongng_ride":0,"done_ride":1620,"cancel_ride":1370,"drvr_cancel":743,"rider_cancel":622,"earning":256080,"dist":12914.778,"avg_dist_pr_trip":7.9721,"avg_fare":158.0741,"srch_to_e_rate":0.9943,"e_to_q_srch_rate":0.5037,"q_accept_rate":0.4785,"q_to_bkng_rate":0.998,"bkng_cancel_rate":0.4579,"cnvr_rate":0.1295},{"ward_num":"144","srch_fr_e":5214,"srch_which_got_e":5193,"srch_fr_q":2373,"srch_which_got_q":990,"booking":987,"ongng_ride":0,"done_ride":473,"cancel_ride":514,"drvr_cancel":273,"rider_cancel":241,"earning":82962,"dist":4096.392,"avg_dist_pr_trip":8.6604,"avg_fare":175.3953,"srch_to_e_rate":0.996,"e_to_q_srch_rate":0.457,"q_accept_rate":0.4172,"q_to_bkng_rate":0.997,"bkng_cancel_rate":0.5208,"cnvr_rate":0.0907},{"ward_num":"145","srch_fr_e":7462,"srch_which_got_e":7442,"srch_fr_q":3645,"srch_which_got_q":1503,"booking":1498,"ongng_ride":0,"done_ride":739,"cancel_ride":759,"drvr_cancel":406,"rider_cancel":347,"earning":122726,"dist":6380.559,"avg_dist_pr_trip":8.634,"avg_fare":166.0704,"srch_to_e_rate":0.9973,"e_to_q_srch_rate":0.4898,"q_accept_rate":0.4123,"q_to_bkng_rate":0.9967,"bkng_cancel_rate":0.5067,"cnvr_rate":0.099},{"ward_num":"146","srch_fr_e":6224,"srch_which_got_e":6194,"srch_fr_q":2656,"srch_which_got_q":1231,"booking":1221,"ongng_ride":0,"done_ride":583,"cancel_ride":638,"drvr_cancel":308,"rider_cancel":328,"earning":94203,"dist":4895.085,"avg_dist_pr_trip":8.3964,"avg_fare":161.5832,"srch_to_e_rate":0.9952,"e_to_q_srch_rate":0.4288,"q_accept_rate":0.4635,"q_to_bkng_rate":0.9919,"bkng_cancel_rate":0.5225,"cnvr_rate":0.0937},{"ward_num":"147","srch_fr_e":11989,"srch_which_got_e":11945,"srch_fr_q":5805,"srch_which_got_q":2695,"booking":2690,"ongng_ride":0,"done_ride":1378,"cancel_ride":1311,"drvr_cancel":687,"rider_cancel":615,"earning":234842,"dist":12279.348,"avg_dist_pr_trip":8.911,"avg_fare":170.4224,"srch_to_e_rate":0.9963,"e_to_q_srch_rate":0.486,"q_accept_rate":0.4643,"q_to_bkng_rate":0.9981,"bkng_cancel_rate":0.4874,"cnvr_rate":0.1149},{"ward_num":"148","srch_fr_e":5893,"srch_which_got_e":5872,"srch_fr_q":2908,"srch_which_got_q":1120,"booking":1116,"ongng_ride":0,"done_ride":550,"cancel_ride":566,"drvr_cancel":291,"rider_cancel":273,"earning":87775,"dist":4517.473,"avg_dist_pr_trip":8.2136,"avg_fare":159.5909,"srch_to_e_rate":0.9964,"e_to_q_srch_rate":0.4952,"q_accept_rate":0.3851,"q_to_bkng_rate":0.9964,"bkng_cancel_rate":0.5072,"cnvr_rate":0.0933},{"ward_num":"149","srch_fr_e":13059,"srch_which_got_e":13010,"srch_fr_q":6970,"srch_which_got_q":3265,"booking":3257,"ongng_ride":0,"done_ride":1722,"cancel_ride":1534,"drvr_cancel":799,"rider_cancel":725,"earning":274414,"dist":13986.276,"avg_dist_pr_trip":8.1221,"avg_fare":159.3577,"srch_to_e_rate":0.9962,"e_to_q_srch_rate":0.5357,"q_accept_rate":0.4684,"q_to_bkng_rate":0.9975,"bkng_cancel_rate":0.471,"cnvr_rate":0.1319},{"ward_num":"150","srch_fr_e":7348,"srch_which_got_e":7340,"srch_fr_q":3307,"srch_which_got_q":1537,"booking":1530,"ongng_ride":0,"done_ride":716,"cancel_ride":813,"drvr_cancel":410,"rider_cancel":400,"earning":126590,"dist":6659.253,"avg_dist_pr_trip":9.3006,"avg_fare":176.8017,"srch_to_e_rate":0.9989,"e_to_q_srch_rate":0.4505,"q_accept_rate":0.4648,"q_to_bkng_rate":0.9954,"bkng_cancel_rate":0.5314,"cnvr_rate":0.0974},{"ward_num":"151","srch_fr_e":10740,"srch_which_got_e":10709,"srch_fr_q":5403,"srch_which_got_q":2312,"booking":2303,"ongng_ride":0,"done_ride":1143,"cancel_ride":1160,"drvr_cancel":578,"rider_cancel":572,"earning":194071,"dist":10023.45,"avg_dist_pr_trip":8.7694,"avg_fare":169.7909,"srch_to_e_rate":0.9971,"e_to_q_srch_rate":0.5045,"q_accept_rate":0.4279,"q_to_bkng_rate":0.9961,"bkng_cancel_rate":0.5037,"cnvr_rate":0.1064},{"ward_num":"152","srch_fr_e":12253,"srch_which_got_e":12221,"srch_fr_q":6638,"srch_which_got_q":3246,"booking":3244,"ongng_ride":0,"done_ride":1739,"cancel_ride":1505,"drvr_cancel":832,"rider_cancel":660,"earning":260080,"dist":13048.658,"avg_dist_pr_trip":7.5035,"avg_fare":149.5572,"srch_to_e_rate":0.9974,"e_to_q_srch_rate":0.5432,"q_accept_rate":0.489,"q_to_bkng_rate":0.9994,"bkng_cancel_rate":0.4639,"cnvr_rate":0.1419},{"ward_num":"153","srch_fr_e":12230,"srch_which_got_e":12195,"srch_fr_q":5825,"srch_which_got_q":2622,"booking":2609,"ongng_ride":0,"done_ride":1275,"cancel_ride":1334,"drvr_cancel":646,"rider_cancel":675,"earning":222593,"dist":11421.945,"avg_dist_pr_trip":8.9584,"avg_fare":174.5827,"srch_to_e_rate":0.9971,"e_to_q_srch_rate":0.4777,"q_accept_rate":0.4501,"q_to_bkng_rate":0.995,"bkng_cancel_rate":0.5113,"cnvr_rate":0.1043},{"ward_num":"154","srch_fr_e":8416,"srch_which_got_e":8379,"srch_fr_q":3944,"srch_which_got_q":1852,"booking":1849,"ongng_ride":0,"done_ride":952,"cancel_ride":897,"drvr_cancel":470,"rider_cancel":426,"earning":161443,"dist":8557.755,"avg_dist_pr_trip":8.9892,"avg_fare":169.583,"srch_to_e_rate":0.9956,"e_to_q_srch_rate":0.4707,"q_accept_rate":0.4696,"q_to_bkng_rate":0.9984,"bkng_cancel_rate":0.4851,"cnvr_rate":0.1131},{"ward_num":"155","srch_fr_e":15326,"srch_which_got_e":15277,"srch_fr_q":6908,"srch_which_got_q":3650,"booking":3637,"ongng_ride":0,"done_ride":1891,"cancel_ride":1746,"drvr_cancel":808,"rider_cancel":930,"earning":275882,"dist":14172.581,"avg_dist_pr_trip":7.4948,"avg_fare":145.8921,"srch_to_e_rate":0.9968,"e_to_q_srch_rate":0.4522,"q_accept_rate":0.5284,"q_to_bkng_rate":0.9964,"bkng_cancel_rate":0.4801,"cnvr_rate":0.1234},{"ward_num":"156","srch_fr_e":16870,"srch_which_got_e":16777,"srch_fr_q":7857,"srch_which_got_q":3125,"booking":3114,"ongng_ride":0,"done_ride":1562,"cancel_ride":1551,"drvr_cancel":769,"rider_cancel":768,"earning":307825,"dist":16191.018,"avg_dist_pr_trip":10.3656,"avg_fare":197.0711,"srch_to_e_rate":0.9945,"e_to_q_srch_rate":0.4683,"q_accept_rate":0.3977,"q_to_bkng_rate":0.9965,"bkng_cancel_rate":0.4981,"cnvr_rate":0.0926},{"ward_num":"157","srch_fr_e":9141,"srch_which_got_e":9075,"srch_fr_q":4911,"srch_which_got_q":1598,"booking":1591,"ongng_ride":0,"done_ride":810,"cancel_ride":781,"drvr_cancel":382,"rider_cancel":395,"earning":163787,"dist":8597.741,"avg_dist_pr_trip":10.6145,"avg_fare":202.2062,"srch_to_e_rate":0.9928,"e_to_q_srch_rate":0.5412,"q_accept_rate":0.3254,"q_to_bkng_rate":0.9956,"bkng_cancel_rate":0.4909,"cnvr_rate":0.0886},{"ward_num":"158","srch_fr_e":3637,"srch_which_got_e":3608,"srch_fr_q":2055,"srch_which_got_q":582,"booking":578,"ongng_ride":0,"done_ride":246,"cancel_ride":332,"drvr_cancel":145,"rider_cancel":185,"earning":45270,"dist":2322.904,"avg_dist_pr_trip":9.4427,"avg_fare":184.0244,"srch_to_e_rate":0.992,"e_to_q_srch_rate":0.5696,"q_accept_rate":0.2832,"q_to_bkng_rate":0.9931,"bkng_cancel_rate":0.5744,"cnvr_rate":0.0676},{"ward_num":"159","srch_fr_e":6426,"srch_which_got_e":6361,"srch_fr_q":2395,"srch_which_got_q":1178,"booking":1176,"ongng_ride":0,"done_ride":615,"cancel_ride":561,"drvr_cancel":238,"rider_cancel":318,"earning":169675,"dist":7688.852,"avg_dist_pr_trip":12.5022,"avg_fare":275.8943,"srch_to_e_rate":0.9899,"e_to_q_srch_rate":0.3765,"q_accept_rate":0.4919,"q_to_bkng_rate":0.9983,"bkng_cancel_rate":0.477,"cnvr_rate":0.0957},{"ward_num":"160","srch_fr_e":8992,"srch_which_got_e":8974,"srch_fr_q":3094,"srch_which_got_q":1446,"booking":1440,"ongng_ride":0,"done_ride":750,"cancel_ride":690,"drvr_cancel":366,"rider_cancel":318,"earning":116786,"dist":6081.176,"avg_dist_pr_trip":8.1082,"avg_fare":155.7147,"srch_to_e_rate":0.998,"e_to_q_srch_rate":0.3448,"q_accept_rate":0.4674,"q_to_bkng_rate":0.9959,"bkng_cancel_rate":0.4792,"cnvr_rate":0.0834},{"ward_num":"161","srch_fr_e":7461,"srch_which_got_e":7426,"srch_fr_q":3094,"srch_which_got_q":1905,"booking":1901,"ongng_ride":0,"done_ride":1015,"cancel_ride":885,"drvr_cancel":471,"rider_cancel":408,"earning":143598,"dist":7086.697,"avg_dist_pr_trip":6.982,"avg_fare":141.4759,"srch_to_e_rate":0.9953,"e_to_q_srch_rate":0.4166,"q_accept_rate":0.6157,"q_to_bkng_rate":0.9979,"bkng_cancel_rate":0.4655,"cnvr_rate":0.136},{"ward_num":"162","srch_fr_e":8739,"srch_which_got_e":8719,"srch_fr_q":3974,"srch_which_got_q":2254,"booking":2251,"ongng_ride":0,"done_ride":1242,"cancel_ride":1008,"drvr_cancel":569,"rider_cancel":435,"earning":212822,"dist":10979.952,"avg_dist_pr_trip":8.8405,"avg_fare":171.3543,"srch_to_e_rate":0.9977,"e_to_q_srch_rate":0.4558,"q_accept_rate":0.5672,"q_to_bkng_rate":0.9987,"bkng_cancel_rate":0.4478,"cnvr_rate":0.1421},{"ward_num":"163","srch_fr_e":5761,"srch_which_got_e":5742,"srch_fr_q":2794,"srch_which_got_q":1652,"booking":1643,"ongng_ride":0,"done_ride":902,"cancel_ride":741,"drvr_cancel":364,"rider_cancel":374,"earning":125802,"dist":5991.562,"avg_dist_pr_trip":6.6425,"avg_fare":139.4701,"srch_to_e_rate":0.9967,"e_to_q_srch_rate":0.4866,"q_accept_rate":0.5913,"q_to_bkng_rate":0.9946,"bkng_cancel_rate":0.451,"cnvr_rate":0.1566},{"ward_num":"164","srch_fr_e":5792,"srch_which_got_e":5763,"srch_fr_q":2646,"srch_which_got_q":1661,"booking":1657,"ongng_ride":0,"done_ride":1000,"cancel_ride":656,"drvr_cancel":351,"rider_cancel":303,"earning":151644,"dist":7376.64,"avg_dist_pr_trip":7.3766,"avg_fare":151.644,"srch_to_e_rate":0.995,"e_to_q_srch_rate":0.4591,"q_accept_rate":0.6277,"q_to_bkng_rate":0.9976,"bkng_cancel_rate":0.3959,"cnvr_rate":0.1727},{"ward_num":"165","srch_fr_e":10097,"srch_which_got_e":10058,"srch_fr_q":5357,"srch_which_got_q":2741,"booking":2738,"ongng_ride":0,"done_ride":1441,"cancel_ride":1297,"drvr_cancel":668,"rider_cancel":625,"earning":217844,"dist":10838.29,"avg_dist_pr_trip":7.5214,"avg_fare":151.1756,"srch_to_e_rate":0.9961,"e_to_q_srch_rate":0.5326,"q_accept_rate":0.5117,"q_to_bkng_rate":0.9989,"bkng_cancel_rate":0.4737,"cnvr_rate":0.1427},{"ward_num":"166","srch_fr_e":3827,"srch_which_got_e":3810,"srch_fr_q":1544,"srch_which_got_q":858,"booking":856,"ongng_ride":0,"done_ride":432,"cancel_ride":424,"drvr_cancel":175,"rider_cancel":244,"earning":82498,"dist":4155.775,"avg_dist_pr_trip":9.6198,"avg_fare":190.9676,"srch_to_e_rate":0.9956,"e_to_q_srch_rate":0.4052,"q_accept_rate":0.5557,"q_to_bkng_rate":0.9977,"bkng_cancel_rate":0.4953,"cnvr_rate":0.1129},{"ward_num":"167","srch_fr_e":10970,"srch_which_got_e":10928,"srch_fr_q":5243,"srch_which_got_q":3238,"booking":3233,"ongng_ride":0,"done_ride":1877,"cancel_ride":1355,"drvr_cancel":712,"rider_cancel":634,"earning":284088,"dist":14105.33,"avg_dist_pr_trip":7.5148,"avg_fare":151.3522,"srch_to_e_rate":0.9962,"e_to_q_srch_rate":0.4798,"q_accept_rate":0.6176,"q_to_bkng_rate":0.9985,"bkng_cancel_rate":0.4191,"cnvr_rate":0.1711},{"ward_num":"168","srch_fr_e":6157,"srch_which_got_e":6120,"srch_fr_q":2814,"srch_which_got_q":1543,"booking":1538,"ongng_ride":0,"done_ride":841,"cancel_ride":696,"drvr_cancel":361,"rider_cancel":333,"earning":133948,"dist":6621.632,"avg_dist_pr_trip":7.8735,"avg_fare":159.2723,"srch_to_e_rate":0.994,"e_to_q_srch_rate":0.4598,"q_accept_rate":0.5483,"q_to_bkng_rate":0.9968,"bkng_cancel_rate":0.4525,"cnvr_rate":0.1366},{"ward_num":"169","srch_fr_e":19028,"srch_which_got_e":18983,"srch_fr_q":9777,"srch_which_got_q":4569,"booking":4560,"ongng_ride":0,"done_ride":2401,"cancel_ride":2158,"drvr_cancel":1187,"rider_cancel":964,"earning":383420,"dist":19139.221,"avg_dist_pr_trip":7.9714,"avg_fare":159.6918,"srch_to_e_rate":0.9976,"e_to_q_srch_rate":0.515,"q_accept_rate":0.4673,"q_to_bkng_rate":0.998,"bkng_cancel_rate":0.4732,"cnvr_rate":0.1262},{"ward_num":"170","srch_fr_e":32925,"srch_which_got_e":32836,"srch_fr_q":15767,"srch_which_got_q":6973,"booking":6953,"ongng_ride":0,"done_ride":3696,"cancel_ride":3254,"drvr_cancel":1670,"rider_cancel":1564,"earning":589685,"dist":30202.71,"avg_dist_pr_trip":8.1717,"avg_fare":159.5468,"srch_to_e_rate":0.9973,"e_to_q_srch_rate":0.4802,"q_accept_rate":0.4423,"q_to_bkng_rate":0.9971,"bkng_cancel_rate":0.468,"cnvr_rate":0.1123},{"ward_num":"171","srch_fr_e":22357,"srch_which_got_e":22284,"srch_fr_q":11798,"srch_which_got_q":5551,"booking":5543,"ongng_ride":0,"done_ride":3002,"cancel_ride":2541,"drvr_cancel":1330,"rider_cancel":1196,"earning":434431,"dist":22058.448,"avg_dist_pr_trip":7.3479,"avg_fare":144.7139,"srch_to_e_rate":0.9967,"e_to_q_srch_rate":0.5294,"q_accept_rate":0.4705,"q_to_bkng_rate":0.9986,"bkng_cancel_rate":0.4584,"cnvr_rate":0.1343},{"ward_num":"172","srch_fr_e":15002,"srch_which_got_e":14930,"srch_fr_q":8215,"srch_which_got_q":3226,"booking":3214,"ongng_ride":0,"done_ride":1887,"cancel_ride":1323,"drvr_cancel":660,"rider_cancel":656,"earning":275436,"dist":14206.88,"avg_dist_pr_trip":7.5288,"avg_fare":145.965,"srch_to_e_rate":0.9952,"e_to_q_srch_rate":0.5502,"q_accept_rate":0.3927,"q_to_bkng_rate":0.9963,"bkng_cancel_rate":0.4116,"cnvr_rate":0.1258},{"ward_num":"173","srch_fr_e":14359,"srch_which_got_e":14298,"srch_fr_q":7481,"srch_which_got_q":4041,"booking":4012,"ongng_ride":0,"done_ride":2289,"cancel_ride":1720,"drvr_cancel":852,"rider_cancel":856,"earning":339640,"dist":17509.938,"avg_dist_pr_trip":7.6496,"avg_fare":148.3792,"srch_to_e_rate":0.9958,"e_to_q_srch_rate":0.5232,"q_accept_rate":0.5402,"q_to_bkng_rate":0.9928,"bkng_cancel_rate":0.4287,"cnvr_rate":0.1594},{"ward_num":"174","srch_fr_e":29440,"srch_which_got_e":29324,"srch_fr_q":15447,"srch_which_got_q":7138,"booking":7113,"ongng_ride":0,"done_ride":3692,"cancel_ride":3419,"drvr_cancel":1633,"rider_cancel":1763,"earning":613378,"dist":31030.955,"avg_dist_pr_trip":8.4049,"avg_fare":166.1371,"srch_to_e_rate":0.9961,"e_to_q_srch_rate":0.5268,"q_accept_rate":0.4621,"q_to_bkng_rate":0.9965,"bkng_cancel_rate":0.4807,"cnvr_rate":0.1254},{"ward_num":"175","srch_fr_e":23303,"srch_which_got_e":23239,"srch_fr_q":12911,"srch_which_got_q":8181,"booking":8151,"ongng_ride":0,"done_ride":4796,"cancel_ride":3354,"drvr_cancel":1687,"rider_cancel":1639,"earning":646932,"dist":31719.97,"avg_dist_pr_trip":6.6138,"avg_fare":134.8899,"srch_to_e_rate":0.9973,"e_to_q_srch_rate":0.5556,"q_accept_rate":0.6336,"q_to_bkng_rate":0.9963,"bkng_cancel_rate":0.4115,"cnvr_rate":0.2058},{"ward_num":"176","srch_fr_e":22118,"srch_which_got_e":22038,"srch_fr_q":12664,"srch_which_got_q":6624,"booking":6611,"ongng_ride":0,"done_ride":3817,"cancel_ride":2792,"drvr_cancel":1415,"rider_cancel":1356,"earning":601021,"dist":29996.562,"avg_dist_pr_trip":7.8587,"avg_fare":157.459,"srch_to_e_rate":0.9964,"e_to_q_srch_rate":0.5746,"q_accept_rate":0.5231,"q_to_bkng_rate":0.998,"bkng_cancel_rate":0.4223,"cnvr_rate":0.1726},{"ward_num":"177","srch_fr_e":21797,"srch_which_got_e":21738,"srch_fr_q":10470,"srch_which_got_q":5322,"booking":5304,"ongng_ride":0,"done_ride":2697,"cancel_ride":2607,"drvr_cancel":1390,"rider_cancel":1201,"earning":400403,"dist":19981.178,"avg_dist_pr_trip":7.4087,"avg_fare":148.4624,"srch_to_e_rate":0.9973,"e_to_q_srch_rate":0.4816,"q_accept_rate":0.5083,"q_to_bkng_rate":0.9966,"bkng_cancel_rate":0.4915,"cnvr_rate":0.1237},{"ward_num":"178","srch_fr_e":15770,"srch_which_got_e":15737,"srch_fr_q":7864,"srch_which_got_q":4656,"booking":4641,"ongng_ride":0,"done_ride":2582,"cancel_ride":2059,"drvr_cancel":1092,"rider_cancel":951,"earning":394512,"dist":19780.3,"avg_dist_pr_trip":7.6608,"avg_fare":152.7932,"srch_to_e_rate":0.9979,"e_to_q_srch_rate":0.4997,"q_accept_rate":0.5921,"q_to_bkng_rate":0.9968,"bkng_cancel_rate":0.4437,"cnvr_rate":0.1637},{"ward_num":"179","srch_fr_e":29097,"srch_which_got_e":29024,"srch_fr_q":14765,"srch_which_got_q":9214,"booking":9182,"ongng_ride":0,"done_ride":5076,"cancel_ride":4103,"drvr_cancel":2138,"rider_cancel":1942,"earning":730203,"dist":36224.791,"avg_dist_pr_trip":7.1365,"avg_fare":143.854,"srch_to_e_rate":0.9975,"e_to_q_srch_rate":0.5087,"q_accept_rate":0.624,"q_to_bkng_rate":0.9965,"bkng_cancel_rate":0.4469,"cnvr_rate":0.1745},{"ward_num":"180","srch_fr_e":28739,"srch_which_got_e":28674,"srch_fr_q":16469,"srch_which_got_q":5664,"booking":5644,"ongng_ride":0,"done_ride":2378,"cancel_ride":3266,"drvr_cancel":1620,"rider_cancel":1634,"earning":424997,"dist":22426.568,"avg_dist_pr_trip":9.4309,"avg_fare":178.7204,"srch_to_e_rate":0.9977,"e_to_q_srch_rate":0.5744,"q_accept_rate":0.3439,"q_to_bkng_rate":0.9965,"bkng_cancel_rate":0.5787,"cnvr_rate":0.0827},{"ward_num":"181","srch_fr_e":17098,"srch_which_got_e":17061,"srch_fr_q":9149,"srch_which_got_q":5579,"booking":5551,"ongng_ride":0,"done_ride":3028,"cancel_ride":2521,"drvr_cancel":1325,"rider_cancel":1183,"earning":476832,"dist":23991.007,"avg_dist_pr_trip":7.9231,"avg_fare":157.4742,"srch_to_e_rate":0.9978,"e_to_q_srch_rate":0.5363,"q_accept_rate":0.6098,"q_to_bkng_rate":0.995,"bkng_cancel_rate":0.4542,"cnvr_rate":0.1771},{"ward_num":"182","srch_fr_e":20921,"srch_which_got_e":20861,"srch_fr_q":10431,"srch_which_got_q":5299,"booking":5282,"ongng_ride":0,"done_ride":2794,"cancel_ride":2487,"drvr_cancel":1206,"rider_cancel":1264,"earning":453776,"dist":23071.044,"avg_dist_pr_trip":8.2574,"avg_fare":162.4109,"srch_to_e_rate":0.9971,"e_to_q_srch_rate":0.5,"q_accept_rate":0.508,"q_to_bkng_rate":0.9968,"bkng_cancel_rate":0.4708,"cnvr_rate":0.1336},{"ward_num":"183","srch_fr_e":15912,"srch_which_got_e":15833,"srch_fr_q":8562,"srch_which_got_q":3488,"booking":3466,"ongng_ride":0,"done_ride":1544,"cancel_ride":1921,"drvr_cancel":966,"rider_cancel":944,"earning":289340,"dist":15285.059,"avg_dist_pr_trip":9.8996,"avg_fare":187.3964,"srch_to_e_rate":0.995,"e_to_q_srch_rate":0.5408,"q_accept_rate":0.4074,"q_to_bkng_rate":0.9937,"bkng_cancel_rate":0.5542,"cnvr_rate":0.097},{"ward_num":"184","srch_fr_e":16165,"srch_which_got_e":16106,"srch_fr_q":8501,"srch_which_got_q":3705,"booking":3687,"ongng_ride":0,"done_ride":1838,"cancel_ride":1848,"drvr_cancel":897,"rider_cancel":944,"earning":330234,"dist":17414.089,"avg_dist_pr_trip":9.4745,"avg_fare":179.6703,"srch_to_e_rate":0.9964,"e_to_q_srch_rate":0.5278,"q_accept_rate":0.4358,"q_to_bkng_rate":0.9951,"bkng_cancel_rate":0.5012,"cnvr_rate":0.1137},{"ward_num":"185","srch_fr_e":12680,"srch_which_got_e":12631,"srch_fr_q":6379,"srch_which_got_q":2807,"booking":2794,"ongng_ride":0,"done_ride":1299,"cancel_ride":1495,"drvr_cancel":770,"rider_cancel":717,"earning":246160,"dist":13217.709,"avg_dist_pr_trip":10.1753,"avg_fare":189.4996,"srch_to_e_rate":0.9961,"e_to_q_srch_rate":0.505,"q_accept_rate":0.44,"q_to_bkng_rate":0.9954,"bkng_cancel_rate":0.5351,"cnvr_rate":0.1024},{"ward_num":"186","srch_fr_e":12778,"srch_which_got_e":12719,"srch_fr_q":6421,"srch_which_got_q":2779,"booking":2771,"ongng_ride":0,"done_ride":1243,"cancel_ride":1528,"drvr_cancel":755,"rider_cancel":763,"earning":234279,"dist":12235.31,"avg_dist_pr_trip":9.8434,"avg_fare":188.4787,"srch_to_e_rate":0.9954,"e_to_q_srch_rate":0.5048,"q_accept_rate":0.4328,"q_to_bkng_rate":0.9971,"bkng_cancel_rate":0.5514,"cnvr_rate":0.0973},{"ward_num":"187","srch_fr_e":5450,"srch_which_got_e":5420,"srch_fr_q":2622,"srch_which_got_q":1273,"booking":1270,"ongng_ride":0,"done_ride":662,"cancel_ride":607,"drvr_cancel":336,"rider_cancel":267,"earning":111385,"dist":5600.085,"avg_dist_pr_trip":8.4593,"avg_fare":168.2553,"srch_to_e_rate":0.9945,"e_to_q_srch_rate":0.4838,"q_accept_rate":0.4855,"q_to_bkng_rate":0.9976,"bkng_cancel_rate":0.478,"cnvr_rate":0.1215},{"ward_num":"188","srch_fr_e":24640,"srch_which_got_e":24568,"srch_fr_q":12155,"srch_which_got_q":6107,"booking":6093,"ongng_ride":0,"done_ride":2928,"cancel_ride":3164,"drvr_cancel":1769,"rider_cancel":1378,"earning":506078,"dist":26046.7,"avg_dist_pr_trip":8.8957,"avg_fare":172.8408,"srch_to_e_rate":0.9971,"e_to_q_srch_rate":0.4947,"q_accept_rate":0.5024,"q_to_bkng_rate":0.9977,"bkng_cancel_rate":0.5193,"cnvr_rate":0.1188},{"ward_num":"189","srch_fr_e":14090,"srch_which_got_e":14018,"srch_fr_q":6620,"srch_which_got_q":2968,"booking":2952,"ongng_ride":0,"done_ride":1453,"cancel_ride":1497,"drvr_cancel":785,"rider_cancel":705,"earning":275597,"dist":15034.864,"avg_dist_pr_trip":10.3475,"avg_fare":189.6745,"srch_to_e_rate":0.9949,"e_to_q_srch_rate":0.4722,"q_accept_rate":0.4483,"q_to_bkng_rate":0.9946,"bkng_cancel_rate":0.5071,"cnvr_rate":0.1031},{"ward_num":"190","srch_fr_e":7984,"srch_which_got_e":7910,"srch_fr_q":3665,"srch_which_got_q":1840,"booking":1834,"ongng_ride":0,"done_ride":869,"cancel_ride":964,"drvr_cancel":510,"rider_cancel":446,"earning":171697,"dist":9420.607,"avg_dist_pr_trip":10.8407,"avg_fare":197.58,"srch_to_e_rate":0.9907,"e_to_q_srch_rate":0.4633,"q_accept_rate":0.502,"q_to_bkng_rate":0.9967,"bkng_cancel_rate":0.5256,"cnvr_rate":0.1088},{"ward_num":"191","srch_fr_e":7516,"srch_which_got_e":7490,"srch_fr_q":3250,"srch_which_got_q":1772,"booking":1768,"ongng_ride":0,"done_ride":900,"cancel_ride":867,"drvr_cancel":416,"rider_cancel":449,"earning":170778,"dist":8996.924,"avg_dist_pr_trip":9.9966,"avg_fare":189.7533,"srch_to_e_rate":0.9965,"e_to_q_srch_rate":0.4339,"q_accept_rate":0.5452,"q_to_bkng_rate":0.9977,"bkng_cancel_rate":0.4904,"cnvr_rate":0.1197},{"ward_num":"192","srch_fr_e":6495,"srch_which_got_e":6448,"srch_fr_q":2876,"srch_which_got_q":1075,"booking":1069,"ongng_ride":0,"done_ride":509,"cancel_ride":559,"drvr_cancel":273,"rider_cancel":282,"earning":117004,"dist":6119.971,"avg_dist_pr_trip":12.0235,"avg_fare":229.8703,"srch_to_e_rate":0.9928,"e_to_q_srch_rate":0.446,"q_accept_rate":0.3738,"q_to_bkng_rate":0.9944,"bkng_cancel_rate":0.5229,"cnvr_rate":0.0784},{"ward_num":"193","srch_fr_e":13161,"srch_which_got_e":13092,"srch_fr_q":6117,"srch_which_got_q":2782,"booking":2769,"ongng_ride":0,"done_ride":1306,"cancel_ride":1463,"drvr_cancel":732,"rider_cancel":722,"earning":246592,"dist":13305.441,"avg_dist_pr_trip":10.1879,"avg_fare":188.8147,"srch_to_e_rate":0.9948,"e_to_q_srch_rate":0.4672,"q_accept_rate":0.4548,"q_to_bkng_rate":0.9953,"bkng_cancel_rate":0.5283,"cnvr_rate":0.0992},{"ward_num":"194","srch_fr_e":10669,"srch_which_got_e":10625,"srch_fr_q":4421,"srch_which_got_q":2484,"booking":2480,"ongng_ride":0,"done_ride":1195,"cancel_ride":1285,"drvr_cancel":594,"rider_cancel":682,"earning":245638,"dist":13563.52,"avg_dist_pr_trip":11.3502,"avg_fare":205.5548,"srch_to_e_rate":0.9959,"e_to_q_srch_rate":0.4161,"q_accept_rate":0.5619,"q_to_bkng_rate":0.9984,"bkng_cancel_rate":0.5181,"cnvr_rate":0.112},{"ward_num":"195","srch_fr_e":5732,"srch_which_got_e":5700,"srch_fr_q":2338,"srch_which_got_q":1386,"booking":1371,"ongng_ride":0,"done_ride":624,"cancel_ride":746,"drvr_cancel":315,"rider_cancel":429,"earning":119868,"dist":6495.682,"avg_dist_pr_trip":10.4097,"avg_fare":192.0962,"srch_to_e_rate":0.9944,"e_to_q_srch_rate":0.4102,"q_accept_rate":0.5928,"q_to_bkng_rate":0.9892,"bkng_cancel_rate":0.5441,"cnvr_rate":0.1089},{"ward_num":"196","srch_fr_e":6615,"srch_which_got_e":6567,"srch_fr_q":2937,"srch_which_got_q":987,"booking":985,"ongng_ride":0,"done_ride":491,"cancel_ride":494,"drvr_cancel":234,"rider_cancel":257,"earning":124195,"dist":6741.334,"avg_dist_pr_trip":13.7298,"avg_fare":252.943,"srch_to_e_rate":0.9927,"e_to_q_srch_rate":0.4472,"q_accept_rate":0.3361,"q_to_bkng_rate":0.998,"bkng_cancel_rate":0.5015,"cnvr_rate":0.0742},{"ward_num":"197","srch_fr_e":29631,"srch_which_got_e":29460,"srch_fr_q":11442,"srch_which_got_q":5053,"booking":5026,"ongng_ride":0,"done_ride":2378,"cancel_ride":2647,"drvr_cancel":1313,"rider_cancel":1321,"earning":543199,"dist":30467.078,"avg_dist_pr_trip":12.8121,"avg_fare":228.4268,"srch_to_e_rate":0.9942,"e_to_q_srch_rate":0.3884,"q_accept_rate":0.4416,"q_to_bkng_rate":0.9947,"bkng_cancel_rate":0.5267,"cnvr_rate":0.0803},{"ward_num":"198","srch_fr_e":8386,"srch_which_got_e":8235,"srch_fr_q":3264,"srch_which_got_q":1239,"booking":1235,"ongng_ride":0,"done_ride":588,"cancel_ride":647,"drvr_cancel":306,"rider_cancel":338,"earning":140268,"dist":7747.285,"avg_dist_pr_trip":13.1757,"avg_fare":238.551,"srch_to_e_rate":0.982,"e_to_q_srch_rate":0.3964,"q_accept_rate":0.3796,"q_to_bkng_rate":0.9968,"bkng_cancel_rate":0.5239,"cnvr_rate":0.0701},{"ward_num":"199","srch_fr_e":1044,"srch_which_got_e":951,"srch_fr_q":388,"srch_which_got_q":95,"booking":95,"ongng_ride":0,"done_ride":44,"cancel_ride":51,"drvr_cancel":17,"rider_cancel":33,"earning":13524,"dist":783.866,"avg_dist_pr_trip":17.8151,"avg_fare":307.3636,"srch_to_e_rate":0.9109,"e_to_q_srch_rate":0.408,"q_accept_rate":0.2448,"q_to_bkng_rate":1,"bkng_cancel_rate":0.5368,"cnvr_rate":0.0421},{"ward_num":"200","srch_fr_e":6207,"srch_which_got_e":6110,"srch_fr_q":1621,"srch_which_got_q":861,"booking":854,"ongng_ride":0,"done_ride":425,"cancel_ride":428,"drvr_cancel":192,"rider_cancel":234,"earning":110002,"dist":6727.594,"avg_dist_pr_trip":15.8296,"avg_fare":258.8282,"srch_to_e_rate":0.9844,"e_to_q_srch_rate":0.2653,"q_accept_rate":0.5312,"q_to_bkng_rate":0.9919,"bkng_cancel_rate":0.5012,"cnvr_rate":0.0685},{"ward_num":"w_0","srch_fr_e":717117,"srch_which_got_e":683124,"srch_fr_q":262203,"srch_which_got_q":123749,"booking":123225,"ongng_ride":0,"done_ride":62369,"cancel_ride":60823,"drvr_cancel":30524,"rider_cancel":29881,"earning":13165774,"dist":704228.957,"avg_dist_pr_trip":11.2913,"avg_fare":211.0948,"srch_to_e_rate":0.9526,"e_to_q_srch_rate":0.3838,"q_accept_rate":0.472,"q_to_bkng_rate":0.9958,"bkng_cancel_rate":0.4936,"cnvr_rate":0.087}]
