[{"srch_fr_e":475754,"srch_which_got_e":474922,"srch_fr_q":383691,"srch_which_got_q":171889,"booking":171346,"ongng_ride":499,"done_ride":110200,"cancel_ride":60576,"drvr_cancel":35507,"rider_cancel":25025,"earning":17061255,"dist":863370.026,"avg_dist_pr_trip":7.496,"avg_fare":146.8616,"srch_to_e_rate":0.9983,"e_to_q_srch_rate":0.8079,"q_accept_rate":0.448,"q_to_bkng_rate":0.9968,"bkng_cancel_rate":0.3535,"cnvr_rate":0.2316,"city":"Bengaluru","booking_type":"Normal","city_code":"BLR"},{"srch_fr_e":1058,"srch_which_got_e":1047,"srch_fr_q":644,"srch_which_got_q":611,"booking":610,"ongng_ride":0,"done_ride":448,"cancel_ride":162,"drvr_cancel":70,"rider_cancel":92,"earning":42376,"dist":2191.193,"avg_dist_pr_trip":5.0838,"avg_fare":100.6854,"srch_to_e_rate":0.9896,"e_to_q_srch_rate":0.6151,"q_accept_rate":0.9488,"q_to_bkng_rate":0.9984,"bkng_cancel_rate":0.2656,"cnvr_rate":0.4234,"city":"Mysore","booking_type":"Normal","city_code":"MYQ"},{"srch_fr_e":2341,"srch_which_got_e":2103,"srch_fr_q":1284,"srch_which_got_q":880,"booking":870,"ongng_ride":1,"done_ride":625,"cancel_ride":244,"drvr_cancel":117,"rider_cancel":126,"earning":38963,"dist":2027.588,"avg_dist_pr_trip":3.5745,"avg_fare":67.258,"srch_to_e_rate":0.8983,"e_to_q_srch_rate":0.6106,"q_accept_rate":0.6854,"q_to_bkng_rate":0.9886,"bkng_cancel_rate":0.2805,"cnvr_rate":0.267,"city":"Tumkuru","booking_type":"Normal","city_code":"TRT"},{"srch_fr_e":2689,"srch_which_got_e":2648,"srch_fr_q":1862,"srch_which_got_q":900,"booking":899,"ongng_ride":5,"done_ride":506,"cancel_ride":388,"drvr_cancel":245,"rider_cancel":143,"earning":77073,"dist":3927.425,"avg_dist_pr_trip":7.1917,"avg_fare":141.4832,"srch_to_e_rate":0.9848,"e_to_q_srch_rate":0.7032,"q_accept_rate":0.4834,"q_to_bkng_rate":0.9989,"bkng_cancel_rate":0.4316,"cnvr_rate":0.1882,"city":"Bengaluru","booking_type":"Purple","city_code":"BLR"},{"srch_fr_e":7,"srch_which_got_e":7,"srch_fr_q":3,"srch_which_got_q":3,"booking":3,"ongng_ride":0,"done_ride":2,"cancel_ride":1,"drvr_cancel":0,"rider_cancel":1,"earning":198,"dist":9.164,"avg_dist_pr_trip":4.582,"avg_fare":99,"srch_to_e_rate":1,"e_to_q_srch_rate":0.4286,"q_accept_rate":1,"q_to_bkng_rate":1,"bkng_cancel_rate":0.3333,"cnvr_rate":0.2857,"city":"Mysore","booking_type":"Purple","city_code":"MYQ"},{"srch_fr_e":85,"srch_which_got_e":76,"srch_fr_q":51,"srch_which_got_q":36,"booking":36,"ongng_ride":0,"done_ride":18,"cancel_ride":18,"drvr_cancel":8,"rider_cancel":10,"earning":1155,"dist":57.975,"avg_dist_pr_trip":3.2422,"avg_fare":63.5769,"srch_to_e_rate":0.8941,"e_to_q_srch_rate":0.6711,"q_accept_rate":0.7059,"q_to_bkng_rate":1,"bkng_cancel_rate":0.5,"cnvr_rate":0.2118,"city":"Tumkuru","booking_type":"Purple","city_code":"TRT"},{"srch_fr_e":77839,"srch_which_got_e":75349,"srch_fr_q":48357,"srch_which_got_q":31769,"booking":26725,"ongng_ride":220,"done_ride":15509,"cancel_ride":10933,"drvr_cancel":5590,"rider_cancel":4546,"earning":4191152,"dist":157728.325,"avg_dist_pr_trip":8.7993,"avg_fare":245.9182,"srch_to_e_rate":0.968,"e_to_q_srch_rate":0.6418,"q_accept_rate":0.657,"q_to_bkng_rate":0.8412,"bkng_cancel_rate":0.4091,"cnvr_rate":0.1992,"city":"Kolkata","booking_type":"Normal","city_code":"CCU"},{"srch_fr_e":5228,"srch_which_got_e":5063,"srch_fr_q":3404,"srch_which_got_q":1899,"booking":1899,"ongng_ride":2,"done_ride":1297,"cancel_ride":598,"drvr_cancel":214,"rider_cancel":383,"earning":328747,"dist":12651.969,"avg_dist_pr_trip":9.5303,"avg_fare":243.3292,"srch_to_e_rate":0.9684,"e_to_q_srch_rate":0.6723,"q_accept_rate":0.5579,"q_to_bkng_rate":1,"bkng_cancel_rate":0.3149,"cnvr_rate":0.2481,"city":"Cochin","booking_type":"Normal","city_code":"COK"},{"srch_fr_e":4284,"srch_which_got_e":4249,"srch_fr_q":1738,"srch_which_got_q":491,"booking":491,"ongng_ride":2,"done_ride":252,"cancel_ride":237,"drvr_cancel":81,"rider_cancel":155,"earning":45858,"dist":1930.236,"avg_dist_pr_trip":7.578,"avg_fare":173.0556,"srch_to_e_rate":0.9918,"e_to_q_srch_rate":0.409,"q_accept_rate":0.2825,"q_to_bkng_rate":1,"bkng_cancel_rate":0.4827,"cnvr_rate":0.0588,"city":"Hyderabad","booking_type":"Normal","city_code":"HYD"},{"srch_fr_e":1,"srch_which_got_e":1,"srch_fr_q":1,"srch_which_got_q":0,"booking":0,"ongng_ride":0,"done_ride":0,"cancel_ride":0,"drvr_cancel":0,"rider_cancel":0,"earning":0,"dist":0,"srch_to_e_rate":1,"e_to_q_srch_rate":1,"q_accept_rate":0,"cnvr_rate":0,"city":"Delhi","booking_type":"Normal","city_code":"DEL"},{"srch_fr_e":22953,"srch_which_got_e":22796,"srch_fr_q":13602,"srch_which_got_q":5529,"booking":5522,"ongng_ride":17,"done_ride":2617,"cancel_ride":2877,"drvr_cancel":1573,"rider_cancel":1298,"earning":517370,"dist":26407.302,"avg_dist_pr_trip":10.0468,"avg_fare":193.9993,"srch_to_e_rate":0.9932,"e_to_q_srch_rate":0.5967,"q_accept_rate":0.4065,"q_to_bkng_rate":0.9987,"bkng_cancel_rate":0.521,"cnvr_rate":0.114,"city":"Chennai","booking_type":"Normal","city_code":"MAA"}]
