[{"srch_fr_e":156743568,"srch_which_got_e":150189361,"srch_fr_q":122508673,"srch_which_got_q":67497333,"booking":66593878,"ongng_ride":0,"done_ride":42394834,"cancel_ride":24183546,"drvr_cancel":14760247,"rider_cancel":9318600,"earning":6073542650,"dist":330838193.539,"avg_dist_pr_trip":7.5121,"avg_fare":136.9342,"srch_to_e_rate":0.9582,"e_to_q_srch_rate":0.8157,"q_accept_rate":0.551,"q_to_bkng_rate":0.9866,"bkng_cancel_rate":0.3631,"cnvr_rate":0.2705,"city":"Bengaluru","booking_type":"Normal","city_code":"BLR"},{"srch_fr_e":589047,"srch_which_got_e":577885,"srch_fr_q":338490,"srch_which_got_q":307304,"booking":302528,"ongng_ride":0,"done_ride":202414,"cancel_ride":100048,"drvr_cancel":42091,"rider_cancel":57302,"earning":17723743,"dist":989297.309,"avg_dist_pr_trip":4.8988,"avg_fare":87.479,"srch_to_e_rate":0.9811,"e_to_q_srch_rate":0.5857,"q_accept_rate":0.9079,"q_to_bkng_rate":0.9845,"bkng_cancel_rate":0.3307,"cnvr_rate":0.3436,"city":"Mysore","booking_type":"Normal","city_code":"MYQ"},{"srch_fr_e":347864,"srch_which_got_e":308702,"srch_fr_q":176652,"srch_which_got_q":118347,"booking":116622,"ongng_ride":0,"done_ride":85042,"cancel_ride":31516,"drvr_cancel":11932,"rider_cancel":19354,"earning":5336830,"dist":272551.812,"avg_dist_pr_trip":3.5489,"avg_fare":69.105,"srch_to_e_rate":0.8874,"e_to_q_srch_rate":0.5722,"q_accept_rate":0.6699,"q_to_bkng_rate":0.9854,"bkng_cancel_rate":0.2702,"cnvr_rate":0.2445,"city":"Tumkuru","booking_type":"Normal","city_code":"TRT"},{"srch_fr_e":697311,"srch_which_got_e":680665,"srch_fr_q":437031,"srch_which_got_q":251605,"booking":249155,"ongng_ride":0,"done_ride":141285,"cancel_ride":107221,"earning":20273948,"dist":1085643.765,"avg_dist_pr_trip":7.4344,"avg_fare":139.2694,"srch_to_e_rate":0.9761,"e_to_q_srch_rate":0.6421,"q_accept_rate":0.5757,"q_to_bkng_rate":0.9903,"bkng_cancel_rate":0.4303,"cnvr_rate":0.2026,"city":"Bengaluru","booking_type":"Purple","city_code":"BLR"},{"srch_fr_e":7721,"srch_which_got_e":7467,"srch_fr_q":3979,"srch_which_got_q":3358,"booking":3347,"ongng_ride":0,"done_ride":1850,"cancel_ride":2036,"earning":157712,"dist":8550.908,"avg_dist_pr_trip":5.2425,"avg_fare":97.9803,"srch_to_e_rate":0.9671,"e_to_q_srch_rate":0.5329,"q_accept_rate":0.8439,"q_to_bkng_rate":0.9967,"bkng_cancel_rate":0.6083,"cnvr_rate":0.2396,"city":"Mysore","booking_type":"Purple","city_code":"MYQ"},{"srch_fr_e":20486329,"srch_which_got_e":19872495,"srch_fr_q":12505492,"srch_which_got_q":7898689,"booking":6501353,"ongng_ride":0,"done_ride":3854021,"cancel_ride":2645891,"drvr_cancel":1177274,"rider_cancel":1208599,"earning":1033893123,"dist":42220248.135,"avg_dist_pr_trip":9.3087,"avg_fare":241.0429,"srch_to_e_rate":0.97,"e_to_q_srch_rate":0.6293,"q_accept_rate":0.6316,"q_to_bkng_rate":0.8231,"bkng_cancel_rate":0.407,"cnvr_rate":0.1881,"city":"Kolkata","booking_type":"Normal","city_code":"CCU"},{"srch_fr_e":25998,"srch_which_got_e":9375,"srch_fr_q":3669,"srch_which_got_q":3452,"booking":3400,"ongng_ride":5,"done_ride":658,"cancel_ride":2687,"drvr_cancel":265,"rider_cancel":1923,"earning":643396,"dist":15729.913,"avg_dist_pr_trip":20.6776,"avg_fare":869.2165,"srch_to_e_rate":0.3606,"e_to_q_srch_rate":0.3914,"q_accept_rate":0.9409,"q_to_bkng_rate":0.9849,"bkng_cancel_rate":0.7903,"cnvr_rate":0.0253,"city":"Siliguri","booking_type":"Normal","city_code":"IXB"},{"srch_fr_e":2133047,"srch_which_got_e":2028300,"srch_fr_q":1293568,"srch_which_got_q":941100,"booking":863826,"ongng_ride":1,"done_ride":592618,"cancel_ride":246235,"drvr_cancel":91337,"rider_cancel":149468,"earning":143879624,"dist":5476316.498,"avg_dist_pr_trip":9.7521,"avg_fare":251.8443,"srch_to_e_rate":0.9509,"e_to_q_srch_rate":0.6378,"q_accept_rate":0.7275,"q_to_bkng_rate":0.9179,"bkng_cancel_rate":0.2851,"cnvr_rate":0.2778,"city":"Cochin","booking_type":"Normal","city_code":"COK"},{"srch_fr_e":1065028,"srch_which_got_e":1049758,"srch_fr_q":468613,"srch_which_got_q":141510,"booking":139850,"ongng_ride":0,"done_ride":59977,"cancel_ride":79810,"drvr_cancel":33384,"rider_cancel":45655,"earning":10107191,"dist":533381.151,"avg_dist_pr_trip":8.9039,"avg_fare":164.5185,"srch_to_e_rate":0.9857,"e_to_q_srch_rate":0.4464,"q_accept_rate":0.302,"q_to_bkng_rate":0.9883,"bkng_cancel_rate":0.5707,"cnvr_rate":0.0563,"city":"Hyderabad","booking_type":"Normal","city_code":"HYD"},{"srch_fr_e":432138,"srch_which_got_e":398836,"srch_fr_q":159826,"srch_which_got_q":47843,"booking":47330,"ongng_ride":0,"done_ride":17489,"cancel_ride":29803,"drvr_cancel":11241,"rider_cancel":18069,"earning":3155769,"dist":207404.186,"avg_dist_pr_trip":13.7188,"avg_fare":202.1794,"srch_to_e_rate":0.9229,"e_to_q_srch_rate":0.4007,"q_accept_rate":0.2993,"q_to_bkng_rate":0.9893,"bkng_cancel_rate":0.6297,"cnvr_rate":0.0405,"city":"Delhi","booking_type":"Normal","city_code":"DEL"},{"srch_fr_e":3756246,"srch_which_got_e":3706102,"srch_fr_q":1773054,"srch_which_got_q":970611,"booking":967650,"ongng_ride":0,"done_ride":506601,"cancel_ride":460796,"drvr_cancel":235306,"rider_cancel":222431,"earning":83050614,"dist":4177113.681,"avg_dist_pr_trip":8.8867,"avg_fare":171.7566,"srch_to_e_rate":0.9867,"e_to_q_srch_rate":0.4784,"q_accept_rate":0.5474,"q_to_bkng_rate":0.9969,"bkng_cancel_rate":0.4762,"cnvr_rate":0.1349,"city":"Chennai","booking_type":"Normal","city_code":"MAA"}]
