[{"srch_fr_e":605917,"srch_which_got_e":603022,"srch_fr_q":472810,"srch_which_got_q":225738,"booking":224304,"ongng_ride":1697,"done_ride":145600,"cancel_ride":76631,"drvr_cancel":42894,"rider_cancel":33568,"earning":23066698,"dist":1182474.898,"avg_dist_pr_trip":7.7826,"avg_fare":150.2531,"srch_to_e_rate":0.9952,"e_to_q_srch_rate":0.7841,"q_accept_rate":0.4774,"q_to_bkng_rate":0.9936,"bkng_cancel_rate":0.3416,"cnvr_rate":0.2403,"city":"Bengaluru","booking_type":"Normal","city_code":"BLR"},{"srch_fr_e":4081,"srch_which_got_e":3829,"srch_fr_q":2413,"srch_which_got_q":1776,"booking":1760,"ongng_ride":7,"done_ride":1081,"cancel_ride":671,"drvr_cancel":316,"rider_cancel":350,"earning":102186,"dist":5866.906,"avg_dist_pr_trip":5.1645,"avg_fare":89.2483,"srch_to_e_rate":0.9383,"e_to_q_srch_rate":0.6302,"q_accept_rate":0.736,"q_to_bkng_rate":0.991,"bkng_cancel_rate":0.3812,"cnvr_rate":0.2649,"city":"Mysore","booking_type":"Normal","city_code":"MYQ"},{"srch_fr_e":11499,"srch_which_got_e":10767,"srch_fr_q":7111,"srch_which_got_q":4857,"booking":4816,"ongng_ride":6,"done_ride":3715,"cancel_ride":1095,"drvr_cancel":551,"rider_cancel":538,"earning":242022,"dist":12834.767,"avg_dist_pr_trip":3.8302,"avg_fare":71.1877,"srch_to_e_rate":0.9363,"e_to_q_srch_rate":0.6604,"q_accept_rate":0.683,"q_to_bkng_rate":0.9916,"bkng_cancel_rate":0.2274,"cnvr_rate":0.3231,"city":"Tumkuru","booking_type":"Normal","city_code":"TRT"},{"srch_fr_e":5205,"srch_which_got_e":4969,"srch_fr_q":2658,"srch_which_got_q":2110,"booking":2087,"ongng_ride":4,"done_ride":1559,"cancel_ride":524,"drvr_cancel":232,"rider_cancel":290,"earning":131859,"dist":5865.964,"avg_dist_pr_trip":3.8107,"avg_fare":84.5857,"srch_to_e_rate":0.9547,"e_to_q_srch_rate":0.5349,"q_accept_rate":0.7938,"q_to_bkng_rate":0.9891,"bkng_cancel_rate":0.2511,"cnvr_rate":0.2995,"city":"Gulbarga","booking_type":"Normal","city_code":"GBI"},{"srch_fr_e":4612,"srch_which_got_e":4527,"srch_fr_q":3142,"srch_which_got_q":1500,"booking":1486,"ongng_ride":11,"done_ride":863,"cancel_ride":609,"drvr_cancel":385,"rider_cancel":223,"earning":141436,"dist":7417.389,"avg_dist_pr_trip":8.0986,"avg_fare":156.0802,"srch_to_e_rate":0.9816,"e_to_q_srch_rate":0.6941,"q_accept_rate":0.4774,"q_to_bkng_rate":0.9907,"bkng_cancel_rate":0.4098,"cnvr_rate":0.1871,"city":"Bengaluru","booking_type":"Purple","city_code":"BLR"},{"srch_fr_e":51,"srch_which_got_e":37,"srch_fr_q":24,"srch_which_got_q":20,"booking":20,"ongng_ride":0,"done_ride":12,"cancel_ride":8,"drvr_cancel":3,"rider_cancel":5,"earning":919,"dist":49.889,"avg_dist_pr_trip":4.2881,"avg_fare":78.2963,"srch_to_e_rate":0.7255,"e_to_q_srch_rate":0.6486,"q_accept_rate":0.8333,"q_to_bkng_rate":1,"bkng_cancel_rate":0.4,"cnvr_rate":0.2353,"city":"Mysore","booking_type":"Purple","city_code":"MYQ"},{"srch_fr_e":445,"srch_which_got_e":367,"srch_fr_q":216,"srch_which_got_q":148,"booking":148,"ongng_ride":1,"done_ride":97,"cancel_ride":50,"drvr_cancel":27,"rider_cancel":22,"earning":6470,"dist":341.043,"avg_dist_pr_trip":3.9644,"avg_fare":72.5965,"srch_to_e_rate":0.8247,"e_to_q_srch_rate":0.5886,"q_accept_rate":0.6852,"q_to_bkng_rate":1,"bkng_cancel_rate":0.3378,"cnvr_rate":0.218,"city":"Tumkuru","booking_type":"Purple","city_code":"TRT"},{"srch_fr_e":125,"srch_which_got_e":117,"srch_fr_q":53,"srch_which_got_q":37,"booking":37,"ongng_ride":1,"done_ride":22,"cancel_ride":14,"drvr_cancel":7,"rider_cancel":6,"earning":1729,"dist":73.914,"avg_dist_pr_trip":3.3439,"avg_fare":78.6765,"srch_to_e_rate":0.936,"e_to_q_srch_rate":0.453,"q_accept_rate":0.6981,"q_to_bkng_rate":1,"bkng_cancel_rate":0.3784,"cnvr_rate":0.176,"city":"Gulbarga","booking_type":"Purple","city_code":"GBI"},{"srch_fr_e":117199,"srch_which_got_e":116965,"srch_fr_q":82182,"srch_which_got_q":56387,"booking":44126,"ongng_ride":535,"done_ride":26215,"cancel_ride":17178,"drvr_cancel":7727,"rider_cancel":8644,"earning":6781828,"dist":277413.318,"avg_dist_pr_trip":19.9969,"avg_fare":598.4158,"srch_to_e_rate":0.998,"e_to_q_srch_rate":0.7026,"q_accept_rate":0.6861,"q_to_bkng_rate":0.7826,"bkng_cancel_rate":0.3893,"cnvr_rate":0.2237,"city":"Kolkata","booking_type":"Normal","city_code":"CCU"},{"srch_fr_e":2466,"srch_which_got_e":2299,"srch_fr_q":1970,"srch_which_got_q":1787,"booking":831,"ongng_ride":4,"done_ride":577,"cancel_ride":246,"drvr_cancel":46,"rider_cancel":118,"earning":799010,"dist":20079.274,"avg_dist_pr_trip":25.6763,"avg_fare":1006.5012,"srch_to_e_rate":0.9323,"e_to_q_srch_rate":0.8569,"q_accept_rate":0.9071,"q_to_bkng_rate":0.465,"bkng_cancel_rate":0.296,"cnvr_rate":0.234,"city":"Siliguri","booking_type":"Normal","city_code":"IXB"},{"srch_fr_e":698,"srch_which_got_e":586,"srch_fr_q":368,"srch_which_got_q":275,"booking":103,"ongng_ride":0,"done_ride":72,"cancel_ride":30,"drvr_cancel":12,"rider_cancel":12,"earning":6184,"dist":353.485,"avg_dist_pr_trip":5.1515,"avg_fare":79.4987,"srch_to_e_rate":0.8395,"e_to_q_srch_rate":0.628,"q_accept_rate":0.7473,"q_to_bkng_rate":0.3745,"bkng_cancel_rate":0.2913,"cnvr_rate":0.1032,"city":"Asansol","booking_type":"Normal","city_code":"ASN"},{"srch_fr_e":2332,"srch_which_got_e":2237,"srch_fr_q":1578,"srch_which_got_q":1315,"booking":840,"ongng_ride":13,"done_ride":594,"cancel_ride":228,"drvr_cancel":64,"rider_cancel":115,"earning":71649,"dist":4461.096,"avg_dist_pr_trip":20.4033,"avg_fare":536.6691,"srch_to_e_rate":0.9593,"e_to_q_srch_rate":0.7054,"q_accept_rate":0.8333,"q_to_bkng_rate":0.6388,"bkng_cancel_rate":0.2714,"cnvr_rate":0.2547,"city":"Durgapur","booking_type":"Normal","city_code":"RDP"},{"srch_fr_e":4288,"srch_which_got_e":4099,"srch_fr_q":2313,"srch_which_got_q":1416,"booking":1393,"ongng_ride":8,"done_ride":893,"cancel_ride":491,"drvr_cancel":162,"rider_cancel":324,"earning":218295,"dist":9118.74,"avg_dist_pr_trip":9.1315,"avg_fare":221.0703,"srch_to_e_rate":0.9559,"e_to_q_srch_rate":0.5643,"q_accept_rate":0.6122,"q_to_bkng_rate":0.9838,"bkng_cancel_rate":0.3525,"cnvr_rate":0.2083,"city":"Cochin","booking_type":"Normal","city_code":"COK"},{"srch_fr_e":2338,"srch_which_got_e":2196,"srch_fr_q":904,"srch_which_got_q":206,"booking":206,"ongng_ride":1,"done_ride":84,"cancel_ride":121,"drvr_cancel":27,"rider_cancel":91,"earning":19213,"dist":893.636,"avg_dist_pr_trip":10.0437,"avg_fare":207.9883,"srch_to_e_rate":0.9393,"e_to_q_srch_rate":0.4117,"q_accept_rate":0.2279,"q_to_bkng_rate":1,"bkng_cancel_rate":0.5874,"cnvr_rate":0.0359,"city":"Hyderabad","booking_type":"Normal","city_code":"HYD"},{"srch_fr_e":573,"srch_which_got_e":545,"srch_fr_q":216,"srch_which_got_q":18,"booking":18,"ongng_ride":0,"done_ride":4,"cancel_ride":14,"drvr_cancel":4,"rider_cancel":10,"earning":959,"dist":58.926,"avg_dist_pr_trip":14.7315,"avg_fare":239.75,"srch_to_e_rate":0.9511,"e_to_q_srch_rate":0.3963,"q_accept_rate":0.0833,"q_to_bkng_rate":1,"bkng_cancel_rate":0.7778,"cnvr_rate":0.007,"city":"Delhi","booking_type":"Normal","city_code":"DEL"},{"srch_fr_e":28591,"srch_which_got_e":28587,"srch_fr_q":16080,"srch_which_got_q":10738,"booking":10069,"ongng_ride":25,"done_ride":6022,"cancel_ride":4011,"drvr_cancel":1772,"rider_cancel":2178,"earning":1219972,"dist":60271.449,"avg_dist_pr_trip":12.4119,"avg_fare":285.4644,"srch_to_e_rate":0.9999,"e_to_q_srch_rate":0.5625,"q_accept_rate":0.6678,"q_to_bkng_rate":0.9377,"bkng_cancel_rate":0.3984,"cnvr_rate":0.2106,"city":"Chennai","booking_type":"Normal","city_code":"MAA"},{"srch_fr_e":8298,"srch_which_got_e":8274,"srch_fr_q":5185,"srch_which_got_q":2843,"booking":2283,"ongng_ride":6,"done_ride":1135,"cancel_ride":1135,"drvr_cancel":463,"rider_cancel":666,"earning":176850,"dist":10144.41,"avg_dist_pr_trip":24.9295,"avg_fare":477.7346,"srch_to_e_rate":0.9971,"e_to_q_srch_rate":0.6267,"q_accept_rate":0.5483,"q_to_bkng_rate":0.803,"bkng_cancel_rate":0.4972,"cnvr_rate":0.1368,"city":"Bhubaneshwar","booking_type":"Normal","city_code":"BBI"},{"srch_fr_e":1088,"srch_which_got_e":940,"srch_fr_q":672,"srch_which_got_q":591,"booking":92,"ongng_ride":0,"done_ride":21,"cancel_ride":71,"drvr_cancel":8,"rider_cancel":46,"earning":4834,"dist":260.477,"avg_dist_pr_trip":19.7011,"avg_fare":393.1169,"srch_to_e_rate":0.864,"e_to_q_srch_rate":0.7149,"q_accept_rate":0.8795,"q_to_bkng_rate":0.1557,"bkng_cancel_rate":0.7717,"cnvr_rate":0.0193,"city":"Cuttack","booking_type":"Normal","city_code":"CTC"},{"srch_fr_e":472,"srch_which_got_e":437,"srch_fr_q":363,"srch_which_got_q":333,"booking":32,"ongng_ride":0,"done_ride":0,"cancel_ride":29,"drvr_cancel":0,"rider_cancel":18,"earning":0,"dist":0,"srch_to_e_rate":0.9258,"e_to_q_srch_rate":0.8307,"q_accept_rate":0.9174,"q_to_bkng_rate":0.0961,"bkng_cancel_rate":0.9062,"cnvr_rate":0,"city":"Puri","booking_type":"Normal","city_code":"PURI"},{"srch_fr_e":432,"srch_which_got_e":386,"srch_fr_q":160,"srch_which_got_q":92,"booking":56,"ongng_ride":1,"done_ride":28,"cancel_ride":27,"drvr_cancel":5,"rider_cancel":21,"earning":4222,"dist":166.231,"avg_dist_pr_trip":5.8461,"avg_fare":152.1168,"srch_to_e_rate":0.8935,"e_to_q_srch_rate":0.4145,"q_accept_rate":0.575,"q_to_bkng_rate":0.6087,"bkng_cancel_rate":0.4821,"cnvr_rate":0.0648,"city":"Thiruvananthapuram","booking_type":"Normal","city_code":"TRV"},{"srch_fr_e":495,"srch_which_got_e":495,"srch_fr_q":279,"srch_which_got_q":116,"booking":99,"ongng_ride":0,"done_ride":73,"cancel_ride":26,"drvr_cancel":8,"rider_cancel":18,"earning":8417,"dist":457.191,"avg_dist_pr_trip":6.7413,"avg_fare":127.3412,"srch_to_e_rate":1,"e_to_q_srch_rate":0.5636,"q_accept_rate":0.4158,"q_to_bkng_rate":0.8534,"bkng_cancel_rate":0.2626,"cnvr_rate":0.1475,"city":"Trichy","booking_type":"Normal","city_code":"TRZ"},{"srch_fr_e":716,"srch_which_got_e":640,"srch_fr_q":382,"srch_which_got_q":292,"booking":138,"ongng_ride":0,"done_ride":63,"cancel_ride":75,"drvr_cancel":21,"rider_cancel":36,"earning":10062,"dist":407.067,"avg_dist_pr_trip":8.9812,"avg_fare":226.9003,"srch_to_e_rate":0.8939,"e_to_q_srch_rate":0.5969,"q_accept_rate":0.7644,"q_to_bkng_rate":0.4726,"bkng_cancel_rate":0.5435,"cnvr_rate":0.088,"city":"Coimbatore","booking_type":"Normal","city_code":"CJB"},{"srch_fr_e":2161,"srch_which_got_e":1865,"srch_fr_q":1084,"srch_which_got_q":510,"booking":428,"ongng_ride":2,"done_ride":205,"cancel_ride":220,"drvr_cancel":69,"rider_cancel":148,"earning":32215,"dist":1424.453,"avg_dist_pr_trip":17.6161,"avg_fare":360.4434,"srch_to_e_rate":0.863,"e_to_q_srch_rate":0.5812,"q_accept_rate":0.4705,"q_to_bkng_rate":0.8392,"bkng_cancel_rate":0.514,"cnvr_rate":0.0949,"city":"Rest of Karnataka","booking_type":"Normal","city_code":"ROK"}]
